{"d4vry": [{"id": 750549, "mc": 304, "oc": 69}], "d4vemn": [{"id": 754567, "mc": 135, "oc": 28}], "d4rkd0": [{"id": 757671, "mc": 16, "oc": 5}], "d4npablo": [{"id": 760927, "mc": 544, "oc": 51}], "d4yve": [{"id": 763536, "mc": 7331, "oc": 1377}], "d4g4": [{"id": 765353, "mc": 111, "oc": 23}], "d4rkdr4g0n44": [{"id": 779588, "mc": 134, "oc": 36}], "d4rklive": [{"id": 791765, "mc": 295, "oc": 56}], "d4t4s3c": [{"id": 796544, "mc": 438, "oc": 28}], "d4idai": [{"id": 796974, "mc": 38, "oc": 7}], "d4rks1d3": [{"id": 800447, "mc": 135, "oc": 24}], "d4nzyy": [{"id": 806623, "mc": 39, "oc": 4}], "d4lbichi": [{"id": 809779, "mc": 4, "oc": 0}], "d4v775513": [{"id": 819676, "mc": 49, "oc": 5}], "d4443": [{"id": 822627, "mc": 7, "oc": 4}], "d4rkcamelot": [{"id": 825854, "mc": 15, "oc": 5}], "d41damon": [{"id": 837930, "mc": 99, "oc": 7}], "d4nznw17": [{"id": 847544, "mc": 73, "oc": 2}], "d4nz": [{"id": 852475, "mc": 43, "oc": 11}], "d4v1d": [{"id": 867994, "mc": 5, "oc": 3}], "d4n1elchen": [{"id": 869725, "mc": 916, "oc": 223}], "d4nkub": [{"id": 880025, "mc": 45, "oc": 24}], "d4c0893": [{"id": 884059, "mc": 46, "oc": 0}], "d4rkzin4823": [{"id": 892151, "mc": 91, "oc": 32}], "d4dustinf": [{"id": 894354, "mc": 86, "oc": 30}], "d4vetheninja": [{"id": 894377, "mc": 164, "oc": 57}], "d4rksh4dw": [{"id": 898901, "mc": 201, "oc": 14}], "d4djgroovymix": [{"id": 900424, "mc": 483, "oc": 100}], "d4vddd": [{"id": 902474, "mc": 22, "oc": 1}], "d4nymq": [{"id": 909238, "mc": 62, "oc": 11}], "d4rklicia": [{"id": 931196, "mc": 4, "oc": 2}], "d4vid": [{"id": 946929, "mc": 376, "oc": 28}], "d4rk0002": [{"id": 950003, "mc": 31, "oc": 8}], "d4cr0k": [{"id": 958483, "mc": 75, "oc": 15}], "d4rant": [{"id": 964052, "mc": 72, "oc": 10}], "d4rkyy": [{"id": 967216, "mc": 6, "oc": 3}], "d4ms19": [{"id": 980729, "mc": 5, "oc": 3}], "d4zzz10": [{"id": 986406, "mc": 81, "oc": 11}], "d4rknesss2169": [{"id": 989725, "mc": 10, "oc": 4}], "d4rkeuse": [{"id": 999561, "mc": 162, "oc": 40}]}