{"nvadr": [{"id": 761246, "mc": 17, "oc": 11}], "nvoc": [{"id": 761346, "mc": 689, "oc": 16}], "nv": [{"id": 764285, "mc": 39, "oc": 6}, {"id": 765766, "mc": 8, "oc": 3}, {"id": 771052, "mc": 30, "oc": 6}, {"id": 803603, "mc": 21, "oc": 1}, {"id": 857150, "mc": 3, "oc": 1}, {"id": 879236, "mc": 361, "oc": 52}, {"id": 896623, "mc": 131, "oc": 48}, {"id": 910582, "mc": 9, "oc": 7}, {"id": 948510, "mc": 25, "oc": 0}], "nvrex": [{"id": 778472, "mc": 43, "oc": 5}], "nvite": [{"id": 782005, "mc": 245, "oc": 1}, {"id": 873309, "mc": 21, "oc": 5}], "nvg": [{"id": 784747, "mc": 464, "oc": 57}, {"id": 874317, "mc": 1611, "oc": 178}], "nvrgiveup": [{"id": 787959, "mc": 9, "oc": 0}], "nvidia": [{"id": 789472, "mc": 1154, "oc": 111}, {"id": 864341, "mc": 116, "oc": 21}, {"id": 926505, "mc": 246, "oc": 62}], "nvcc": [{"id": 800361, "mc": 349, "oc": 45}], "nvshendao": [{"id": 802762, "mc": 89, "oc": 3}], "nvde": [{"id": 810303, "mc": 996, "oc": 10}, {"id": 853068, "mc": 1210, "oc": 19}, {"id": 879840, "mc": 4, "oc": 4}, {"id": 902827, "mc": 31, "oc": 2}, {"id": 927014, "mc": 735, "oc": 15}], "nvu": [{"id": 819308, "mc": 19, "oc": 0}], "nvim": [{"id": 834136, "mc": 520, "oc": 52}, {"id": 901504, "mc": 1, "oc": 0}], "nvp": [{"id": 840299, "mc": 13, "oc": 0}], "nvc": [{"id": 851141, "mc": 71, "oc": 4}], "nvh": [{"id": 852922, "mc": 413, "oc": 68}], "nvia": [{"id": 857122, "mc": 145, "oc": 9}], "nvision": [{"id": 862101, "mc": 20, "oc": 9}], "nvk": [{"id": 887483, "mc": 509, "oc": 107}], "nvl": [{"id": 915745, "mc": 10, "oc": 5}], "nvsn": [{"id": 918956, "mc": 12, "oc": 2}], "nvesting": [{"id": 921017, "mc": 17, "oc": 1}], "nvig": [{"id": 948609, "mc": 7, "oc": 3}], "nvbroke": [{"id": 958325, "mc": 7, "oc": 1}], "nvest": [{"id": 959382, "mc": 3, "oc": 0}], "nvstr": [{"id": 975858, "mc": 332, "oc": 20}], "nvisionz": [{"id": 977087, "mc": 39, "oc": 9}], "nvn": [{"id": 982013, "mc": 23, "oc": 13}, {"id": 995154, "mc": 52, "oc": 15}], "nvhp": [{"id": 983647, "mc": 13, "oc": 2}], "nva": [{"id": 983934, "mc": 6822, "oc": 804}], "nvtt": [{"id": 995611, "mc": 46, "oc": 19}]}