{"xz1z1z1z1z": [{"id": 757078, "mc": 462, "oc": 68}], "xzark": [{"id": 771640, "mc": 74, "oc": 12}], "xza": [{"id": 805780, "mc": 7386, "oc": 2003}], "xz": [{"id": 837252, "mc": 172, "oc": 19}, {"id": 912761, "mc": 158, "oc": 7}, {"id": 952846, "mc": 60, "oc": 19}, {"id": 975961, "mc": 583, "oc": 50}], "xzys": [{"id": 844531, "mc": 335, "oc": 86}], "xzeko": [{"id": 853807, "mc": 75, "oc": 17}], "xzion": [{"id": 877724, "mc": 20, "oc": 5}], "xzanderaven": [{"id": 878501, "mc": 20, "oc": 5}], "xzayo": [{"id": 935907, "mc": 112, "oc": 14}], "xzighz": [{"id": 968079, "mc": 3, "oc": 1}]}