{"yoyoyopo5": [{"id": 750135, "mc": 82, "oc": 41}], "yoloblaziken": [{"id": 750322, "mc": 12, "oc": 10}], "yoniorlax": [{"id": 750959, "mc": 36, "oc": 10}], "yo": [{"id": 751042, "mc": 49, "oc": 8}, {"id": 765456, "mc": 290, "oc": 10}, {"id": 798198, "mc": 327, "oc": 30}, {"id": 808866, "mc": 964, "oc": 70}, {"id": 810907, "mc": 75, "oc": 6}, {"id": 817135, "mc": 8, "oc": 4}, {"id": 823433, "mc": 59, "oc": 20}, {"id": 843095, "mc": 1344, "oc": 124}, {"id": 851853, "mc": 24, "oc": 3}, {"id": 859655, "mc": 24, "oc": 7}, {"id": 869735, "mc": 44, "oc": 12}, {"id": 884616, "mc": 127, "oc": 18}, {"id": 901443, "mc": 60, "oc": 21}, {"id": 904940, "mc": 114, "oc": 40}, {"id": 904940, "mc": 114, "oc": 40}, {"id": 905398, "mc": 262, "oc": 25}, {"id": 926239, "mc": 29, "oc": 3}, {"id": 931712, "mc": 12, "oc": 2}, {"id": 936737, "mc": 72, "oc": 3}, {"id": 958623, "mc": 17, "oc": 3}, {"id": 974708, "mc": 9, "oc": 2}, {"id": 975529, "mc": 19, "oc": 4}, {"id": 996899, "mc": 94, "oc": 28}], "yomic": [{"id": 751757, "mc": 699, "oc": 111}, {"id": 892035, "mc": 62, "oc": 18}], "yordi": [{"id": 751951, "mc": 158, "oc": 21}, {"id": 762642, "mc": 65, "oc": 16}, {"id": 927930, "mc": 343, "oc": 8}, {"id": 988191, "mc": 3, "oc": 1}], "yousaysilver": [{"id": 752412, "mc": 181, "oc": 33}], "yosef": [{"id": 752482, "mc": 1278, "oc": 99}], "your": [{"id": 752571, "mc": 6, "oc": 1}, {"id": 761491, "mc": 32, "oc": 2}, {"id": 768314, "mc": 17, "oc": 2}, {"id": 773495, "mc": 68, "oc": 14}, {"id": 774599, "mc": 15, "oc": 9}, {"id": 774972, "mc": 40, "oc": 10}, {"id": 779604, "mc": 22, "oc": 1}, {"id": 787012, "mc": 8007, "oc": 1753}, {"id": 787690, "mc": 15, "oc": 5}, {"id": 790243, "mc": 2, "oc": 1}, {"id": 805928, "mc": 8, "oc": 2}, {"id": 812831, "mc": 142, "oc": 31}, {"id": 815715, "mc": 12, "oc": 1}, {"id": 816140, "mc": 55, "oc": 25}, {"id": 822138, "mc": 33, "oc": 5}, {"id": 834315, "mc": 22, "oc": 9}, {"id": 844152, "mc": 3, "oc": 1}, {"id": 846398, "mc": 18, "oc": 4}, {"id": 851842, "mc": 55, "oc": 4}, {"id": 871073, "mc": 238, "oc": 52}, {"id": 882734, "mc": 27, "oc": 7}, {"id": 897409, "mc": 33, "oc": 11}, {"id": 904804, "mc": 771, "oc": 200}, {"id": 905619, "mc": 8434, "oc": 874}, {"id": 915553, "mc": 48, "oc": 15}, {"id": 926211, "mc": 23, "oc": 17}, {"id": 937501, "mc": 16, "oc": 5}, {"id": 941364, "mc": 16, "oc": 7}, {"id": 942031, "mc": 589, "oc": 101}, {"id": 947285, "mc": 141, "oc": 19}, {"id": 959495, "mc": 4, "oc": 1}, {"id": 981239, "mc": 113, "oc": 12}, {"id": 982309, "mc": 154, "oc": 10}, {"id": 984935, "mc": 318, "oc": 22}, {"id": 988306, "mc": 6, "oc": 0}, {"id": 991812, "mc": 21, "oc": 7}, {"id": 998576, "mc": 69, "oc": 9}, {"id": 999540, "mc": 180, "oc": 75}], "yourcreepydog": [{"id": 752621, "mc": 341, "oc": 54}], "youka": [{"id": 752836, "mc": 56, "oc": 26}], "youdec": [{"id": 752995, "mc": 6715, "oc": 276}], "yoda0x": [{"id": 753260, "mc": 6036, "oc": 8}], "younesse": [{"id": 754260, "mc": 254, "oc": 25}], "youtube": [{"id": 754778, "mc": 494, "oc": 27}, {"id": 757174, "mc": 287, "oc": 44}, {"id": 770960, "mc": 279, "oc": 37}, {"id": 778218, "mc": 1, "oc": 0}, {"id": 778268, "mc": 30, "oc": 5}, {"id": 779796, "mc": 36, "oc": 5}, {"id": 789376, "mc": 37, "oc": 14}, {"id": 791762, "mc": 267, "oc": 26}, {"id": 804063, "mc": 108, "oc": 0}, {"id": 815253, "mc": 19260, "oc": 3345}, {"id": 823568, "mc": 15, "oc": 3}, {"id": 823926, "mc": 1096, "oc": 142}, {"id": 848831, "mc": 25, "oc": 4}, {"id": 855392, "mc": 5446, "oc": 200}, {"id": 872430, "mc": 98, "oc": 26}, {"id": 889440, "mc": 243, "oc": 29}, {"id": 895323, "mc": 1, "oc": 0}, {"id": 896296, "mc": 26, "oc": 9}, {"id": 902642, "mc": 222, "oc": 10}, {"id": 905145, "mc": 15, "oc": 5}, {"id": 915370, "mc": 135, "oc": 15}, {"id": 918095, "mc": 135, "oc": 19}, {"id": 920952, "mc": 19, "oc": 1}, {"id": 921228, "mc": 34, "oc": 10}, {"id": 924596, "mc": 189, "oc": 3}, {"id": 934346, "mc": 1, "oc": 0}, {"id": 943149, "mc": 15, "oc": 3}, {"id": 948133, "mc": 702, "oc": 62}, {"id": 974099, "mc": 2, "oc": 0}, {"id": 975288, "mc": 14, "oc": 1}, {"id": 994257, "mc": 157, "oc": 34}, {"id": 995560, "mc": 2022, "oc": 141}], "yoboytemo": [{"id": 754944, "mc": 9, "oc": 2}], "yodi": [{"id": 755475, "mc": 222, "oc": 120}, {"id": 796259, "mc": 217, "oc": 123}, {"id": 953559, "mc": 102, "oc": 17}], "yokespai": [{"id": 756134, "mc": 129, "oc": 65}, {"id": 989771, "mc": 110, "oc": 43}], "yoiki": [{"id": 756498, "mc": 4, "oc": 1}], "youngheart80": [{"id": 756606, "mc": 2669, "oc": 204}], "yokai": [{"id": 757531, "mc": 41, "oc": 10}, {"id": 821611, "mc": 15, "oc": 0}], "youknowme": [{"id": 757573, "mc": 2288, "oc": 59}], "yourlocalghost": [{"id": 757768, "mc": 7, "oc": 2}], "yourmothersfavouritehouseguest": [{"id": 757901, "mc": 22, "oc": 2}], "yomi": [{"id": 758052, "mc": 44, "oc": 2}, {"id": 804767, "mc": 10, "oc": 1}, {"id": 859137, "mc": 30, "oc": 7}, {"id": 922534, "mc": 103, "oc": 52}, {"id": 952244, "mc": 297, "oc": 16}, {"id": 976640, "mc": 156, "oc": 15}], "younga": [{"id": 758124, "mc": 2496, "oc": 194}, {"id": 766453, "mc": 2514, "oc": 29}], "yoshiaki": [{"id": 758207, "mc": 70, "oc": 21}, {"id": 810342, "mc": 6, "oc": 1}], "yoot": [{"id": 758219, "mc": 669, "oc": 183}], "yongbokie": [{"id": 758227, "mc": 10, "oc": 1}], "yourfavsamurai": [{"id": 758950, "mc": 2, "oc": 0}], "yotax": [{"id": 758969, "mc": 965, "oc": 10}], "youth": [{"id": 759103, "mc": 874, "oc": 342}, {"id": 762457, "mc": 42, "oc": 5}, {"id": 774931, "mc": 50, "oc": 12}, {"id": 784899, "mc": 13, "oc": 0}, {"id": 833603, "mc": 38, "oc": 0}], "yoydna": [{"id": 759347, "mc": 140, "oc": 56}], "yoichi": [{"id": 759576, "mc": 5, "oc": 0}, {"id": 852257, "mc": 37, "oc": 5}], "yoann": [{"id": 760385, "mc": 16, "oc": 5}, {"id": 875891, "mc": 8, "oc": 2}], "youngmetro261": [{"id": 761878, "mc": 3739, "oc": 232}], "yourboysuper": [{"id": 761995, "mc": 2, "oc": 0}], "yoko": [{"id": 762189, "mc": 8886, "oc": 630}, {"id": 827056, "mc": 14, "oc": 5}, {"id": 870044, "mc": 66, "oc": 22}, {"id": 876615, "mc": 35, "oc": 5}, {"id": 901282, "mc": 19, "oc": 9}, {"id": 942498, "mc": 1, "oc": 0}], "yoshito": [{"id": 763223, "mc": 1, "oc": 0}], "yoel": [{"id": 763678, "mc": 36, "oc": 4}, {"id": 833236, "mc": 313, "oc": 27}, {"id": 902581, "mc": 17, "oc": 3}, {"id": 926133, "mc": 82, "oc": 9}], "yobroitsjo": [{"id": 763894, "mc": 163, "oc": 25}], "yowazpoppin": [{"id": 763905, "mc": 530, "oc": 279}], "yourlily": [{"id": 764054, "mc": 402, "oc": 19}, {"id": 912404, "mc": 44, "oc": 7}], "yopoppy": [{"id": 764070, "mc": 65, "oc": 7}], "yosoy": [{"id": 764172, "mc": 357, "oc": 40}], "yotsubablack": [{"id": 764491, "mc": 17, "oc": 1}, {"id": 959566, "mc": 92, "oc": 8}], "yodokuma": [{"id": 764641, "mc": 106, "oc": 47}], "yojosh": [{"id": 764681, "mc": 54, "oc": 14}], "yoan5": [{"id": 765093, "mc": 11202, "oc": 628}], "yoloderr": [{"id": 765308, "mc": 3, "oc": 0}], "yose": [{"id": 765550, "mc": 239, "oc": 9}, {"id": 770707, "mc": 852, "oc": 258}], "yourboy": [{"id": 765652, "mc": 37, "oc": 3}], "yondupoppinsyall": [{"id": 765704, "mc": 228, "oc": 76}], "youwont": [{"id": 766035, "mc": 252, "oc": 55}], "yoshikawa": [{"id": 766058, "mc": 122, "oc": 13}], "yourstruly": [{"id": 766087, "mc": 24, "oc": 6}], "yofk": [{"id": 766133, "mc": 144, "oc": 22}], "yoneill": [{"id": 766177, "mc": 39, "oc": 1}, {"id": 973577, "mc": 658, "oc": 56}], "yona": [{"id": 766666, "mc": 324, "oc": 67}, {"id": 870736, "mc": 26, "oc": 10}, {"id": 878177, "mc": 170, "oc": 6}], "youngbalerion": [{"id": 766754, "mc": 153, "oc": 43}], "yonel": [{"id": 766812, "mc": 32, "oc": 3}], "yode": [{"id": 767313, "mc": 898, "oc": 158}, {"id": 874838, "mc": 14, "oc": 4}], "yoigo": [{"id": 767655, "mc": 41, "oc": 9}], "york": [{"id": 768796, "mc": 795, "oc": 126}, {"id": 825026, "mc": 279, "oc": 94}], "yorinaki": [{"id": 768982, "mc": 347, "oc": 111}], "yod": [{"id": 769538, "mc": 27, "oc": 7}], "youne": [{"id": 769629, "mc": 410, "oc": 12}, {"id": 802636, "mc": 25, "oc": 3}, {"id": 915088, "mc": 1, "oc": 1}], "yoshi": [{"id": 769631, "mc": 21, "oc": 2}, {"id": 771914, "mc": 51, "oc": 26}, {"id": 773219, "mc": 24, "oc": 1}, {"id": 775396, "mc": 386, "oc": 176}, {"id": 780592, "mc": 635, "oc": 34}, {"id": 842341, "mc": 157, "oc": 1}, {"id": 863438, "mc": 1447, "oc": 281}, {"id": 864917, "mc": 215, "oc": 15}, {"id": 886959, "mc": 64, "oc": 19}, {"id": 898357, "mc": 14, "oc": 4}, {"id": 915247, "mc": 983, "oc": 93}, {"id": 920409, "mc": 20, "oc": 1}, {"id": 922605, "mc": 25, "oc": 2}, {"id": 926021, "mc": 42, "oc": 23}, {"id": 939160, "mc": 2, "oc": 1}, {"id": 950439, "mc": 6, "oc": 2}], "youngjay914": [{"id": 770498, "mc": 159, "oc": 24}], "youngblood": [{"id": 772649, "mc": 211, "oc": 20}, {"id": 947910, "mc": 138, "oc": 23}], "yoshi999": [{"id": 773184, "mc": 169, "oc": 19}], "youngboy": [{"id": 773569, "mc": 22, "oc": 8}], "yon": [{"id": 774616, "mc": 23, "oc": 3}], "yonnifp": [{"id": 774671, "mc": 35, "oc": 6}], "yodha": [{"id": 774856, "mc": 1, "oc": 0}], "yoru": [{"id": 774869, "mc": 461, "oc": 130}, {"id": 878685, "mc": 136, "oc": 61}, {"id": 927360, "mc": 43, "oc": 12}, {"id": 950583, "mc": 4, "oc": 1}], "yongbokieee": [{"id": 775793, "mc": 178, "oc": 29}], "young": [{"id": 776015, "mc": 6, "oc": 1}, {"id": 809290, "mc": 91, "oc": 14}, {"id": 814613, "mc": 22, "oc": 1}, {"id": 817973, "mc": 45, "oc": 2}, {"id": 832798, "mc": 456, "oc": 15}, {"id": 834903, "mc": 6, "oc": 1}, {"id": 856294, "mc": 380, "oc": 43}, {"id": 865673, "mc": 152, "oc": 5}, {"id": 870953, "mc": 32, "oc": 5}, {"id": 910204, "mc": 189, "oc": 21}, {"id": 915427, "mc": 3, "oc": 1}, {"id": 931393, "mc": 212, "oc": 34}, {"id": 938515, "mc": 4387, "oc": 92}, {"id": 944733, "mc": 29, "oc": 6}, {"id": 960529, "mc": 110, "oc": 24}, {"id": 982759, "mc": 2367, "oc": 140}], "yobatman": [{"id": 778953, "mc": 3159, "oc": 176}], "youaintmyfry": [{"id": 778989, "mc": 441, "oc": 13}], "yowveetoo": [{"id": 779866, "mc": 50, "oc": 25}], "yorozuyaeddie": [{"id": 781346, "mc": 49, "oc": 10}], "yoitsfrosty": [{"id": 781470, "mc": 111, "oc": 23}], "yoda1x": [{"id": 782433, "mc": 16, "oc": 9}], "yorick": [{"id": 782443, "mc": 5, "oc": 2}, {"id": 846651, "mc": 244, "oc": 9}, {"id": 901323, "mc": 13, "oc": 6}], "youareinacoma": [{"id": 782982, "mc": 45, "oc": 10}, {"id": 875610, "mc": 93, "oc": 10}], "yojix": [{"id": 782987, "mc": 90, "oc": 5}], "yojo": [{"id": 783081, "mc": 1, "oc": 0}], "younplay": [{"id": 783276, "mc": 4437, "oc": 107}], "yoni": [{"id": 783410, "mc": 16, "oc": 10}, {"id": 788063, "mc": 19, "oc": 4}, {"id": 905183, "mc": 3, "oc": 0}, {"id": 963418, "mc": 850, "oc": 106}], "yorbanu": [{"id": 783639, "mc": 51, "oc": 13}], "yonim": [{"id": 784303, "mc": 118, "oc": 10}], "yoshitero": [{"id": 784517, "mc": 193, "oc": 39}], "yonni": [{"id": 785305, "mc": 969, "oc": 79}], "yoneh": [{"id": 785396, "mc": 3, "oc": 0}], "youcankallmeal": [{"id": 786171, "mc": 42, "oc": 15}], "yourlocalscriptfile": [{"id": 787096, "mc": 6, "oc": 4}], "youngmark": [{"id": 787248, "mc": 17, "oc": 2}], "youlltim": [{"id": 787700, "mc": 19, "oc": 9}, {"id": 835319, "mc": 231, "oc": 58}], "yogurt": [{"id": 787831, "mc": 625, "oc": 145}, {"id": 791075, "mc": 37, "oc": 13}, {"id": 823385, "mc": 13, "oc": 5}, {"id": 838837, "mc": 137, "oc": 9}, {"id": 908426, "mc": 14, "oc": 3}, {"id": 974785, "mc": 227, "oc": 61}, {"id": 986747, "mc": 1245, "oc": 51}, {"id": 992478, "mc": 157, "oc": 32}], "yoeminence": [{"id": 788205, "mc": 677, "oc": 124}, {"id": 881760, "mc": 2, "oc": 1}], "yosiakatsuki": [{"id": 788603, "mc": 299, "oc": 10}], "yonogaming": [{"id": 788813, "mc": 590, "oc": 52}], "yokaifox": [{"id": 788923, "mc": 1549, "oc": 45}], "yoshiiki": [{"id": 788955, "mc": 143, "oc": 14}], "yolo": [{"id": 789186, "mc": 8163, "oc": 1519}, {"id": 826631, "mc": 21, "oc": 2}, {"id": 854450, "mc": 335, "oc": 31}, {"id": 870845, "mc": 1, "oc": 0}, {"id": 874734, "mc": 7, "oc": 4}, {"id": 940478, "mc": 26, "oc": 6}, {"id": 945167, "mc": 15, "oc": 2}, {"id": 988788, "mc": 87, "oc": 30}], "yougha54": [{"id": 790109, "mc": 68, "oc": 21}], "yogirlbrooklyn00": [{"id": 790914, "mc": 1, "oc": 0}], "youfang": [{"id": 791300, "mc": 2248, "oc": 18}], "yonengamer": [{"id": 791613, "mc": 12, "oc": 9}], "yodiguh": [{"id": 791672, "mc": 214, "oc": 29}], "yoon": [{"id": 791753, "mc": 649, "oc": 95}, {"id": 850044, "mc": 1708, "oc": 281}, {"id": 927938, "mc": 10, "oc": 3}, {"id": 931212, "mc": 325, "oc": 40}], "yoman": [{"id": 791758, "mc": 79, "oc": 16}], "yogi": [{"id": 792550, "mc": 46, "oc": 6}, {"id": 805078, "mc": 10, "oc": 4}, {"id": 936643, "mc": 1305, "oc": 137}], "yourguyjai": [{"id": 793030, "mc": 17, "oc": 2}], "yonkykong": [{"id": 793816, "mc": 5, "oc": 1}], "yoonix": [{"id": 795436, "mc": 35, "oc": 2}], "yoitskit": [{"id": 796459, "mc": 8, "oc": 6}], "yoangj": [{"id": 796729, "mc": 34, "oc": 3}], "yohan": [{"id": 796740, "mc": 1708, "oc": 26}, {"id": 958000, "mc": 214, "oc": 9}, {"id": 959193, "mc": 86, "oc": 17}, {"id": 976246, "mc": 333, "oc": 30}], "yoduck": [{"id": 797061, "mc": 2, "oc": 1}], "yoyoo0101": [{"id": 797534, "mc": 105, "oc": 7}], "yonasalem": [{"id": 797786, "mc": 140, "oc": 1}], "youmingd": [{"id": 798367, "mc": 27, "oc": 5}], "yoo": [{"id": 798530, "mc": 1, "oc": 0}, {"id": 818863, "mc": 42, "oc": 17}, {"id": 926703, "mc": 17, "oc": 6}, {"id": 986583, "mc": 7, "oc": 1}], "yolidl91": [{"id": 798547, "mc": 53, "oc": 8}], "yoruichi": [{"id": 798691, "mc": 43, "oc": 14}], "youe": [{"id": 799111, "mc": 5, "oc": 1}], "yooperguy": [{"id": 799528, "mc": 2, "oc": 0}], "yo2": [{"id": 799709, "mc": 43, "oc": 11}], "yoshinaga": [{"id": 801231, "mc": 1, "oc": 0}], "yoland": [{"id": 802340, "mc": 419, "oc": 50}], "yossy": [{"id": 802825, "mc": 2, "oc": 0}, {"id": 933994, "mc": 13, "oc": 4}], "yourself": [{"id": 802964, "mc": 981, "oc": 36}, {"id": 876109, "mc": 1086, "oc": 133}], "yougetpownd": [{"id": 803132, "mc": 35, "oc": 16}], "yourlewdwaifu": [{"id": 803257, "mc": 31, "oc": 2}], "yoone": [{"id": 804054, "mc": 265, "oc": 30}], "yok": [{"id": 804321, "mc": 66, "oc": 13}, {"id": 868609, "mc": 1467, "oc": 257}, {"id": 939356, "mc": 42, "oc": 10}], "yot": [{"id": 804449, "mc": 7, "oc": 1}], "yotubeto": [{"id": 804702, "mc": 46, "oc": 7}], "yote": [{"id": 805076, "mc": 68, "oc": 28}], "yorvex": [{"id": 805336, "mc": 221, "oc": 25}], "yokylespringer": [{"id": 805378, "mc": 15, "oc": 4}], "yonestra": [{"id": 805511, "mc": 35, "oc": 2}], "yol": [{"id": 806880, "mc": 24, "oc": 10}, {"id": 971370, "mc": 206, "oc": 19}], "yourlizardfriend": [{"id": 807330, "mc": 54, "oc": 35}], "youmayknowbeno": [{"id": 807716, "mc": 72, "oc": 19}], "yourveganfallacyi": [{"id": 808155, "mc": 88, "oc": 10}], "yoofox": [{"id": 808345, "mc": 26, "oc": 5}], "yoi": [{"id": 808421, "mc": 130, "oc": 23}, {"id": 914370, "mc": 176, "oc": 39}, {"id": 992145, "mc": 68, "oc": 19}], "yokomany": [{"id": 810325, "mc": 9, "oc": 3}], "youkai": [{"id": 810514, "mc": 40, "oc": 9}, {"id": 841793, "mc": 9, "oc": 4}], "yoyo": [{"id": 811485, "mc": 149, "oc": 39}, {"id": 815015, "mc": 1577, "oc": 106}, {"id": 818767, "mc": 250, "oc": 30}, {"id": 822867, "mc": 13, "oc": 6}, {"id": 827117, "mc": 74, "oc": 12}, {"id": 974930, "mc": 26, "oc": 8}], "yosquid": [{"id": 811626, "mc": 22, "oc": 5}], "yo252yo": [{"id": 812591, "mc": 204, "oc": 53}], "yoda": [{"id": 812722, "mc": 1, "oc": 0}, {"id": 817109, "mc": 27, "oc": 6}, {"id": 861861, "mc": 149, "oc": 6}, {"id": 873169, "mc": 11, "oc": 6}, {"id": 876444, "mc": 61, "oc": 11}, {"id": 903900, "mc": 1357, "oc": 97}, {"id": 920822, "mc": 7, "oc": 1}, {"id": 922042, "mc": 79, "oc": 16}, {"id": 935398, "mc": 1399, "oc": 88}, {"id": 960892, "mc": 41, "oc": 8}, {"id": 992395, "mc": 111, "oc": 35}], "yourheckinmom": [{"id": 813077, "mc": 6, "oc": 2}], "youngone": [{"id": 813208, "mc": 1205, "oc": 10}, {"id": 888928, "mc": 3499, "oc": 121}], "yoooooooo1": [{"id": 813652, "mc": 145, "oc": 21}], "yonian": [{"id": 814252, "mc": 169, "oc": 24}], "yoyozakizun": [{"id": 814375, "mc": 33, "oc": 4}], "yourownerer": [{"id": 814388, "mc": 200, "oc": 70}], "yojimbo": [{"id": 814675, "mc": 1, "oc": 1}], "youmu": [{"id": 814879, "mc": 7, "oc": 3}, {"id": 836636, "mc": 2, "oc": 1}], "yota": [{"id": 815145, "mc": 33, "oc": 9}, {"id": 951941, "mc": 23, "oc": 8}], "yone": [{"id": 816881, "mc": 909, "oc": 88}, {"id": 829853, "mc": 14, "oc": 6}, {"id": 876707, "mc": 134, "oc": 14}, {"id": 910039, "mc": 3, "oc": 2}, {"id": 958309, "mc": 110, "oc": 19}], "youknowwho": [{"id": 819072, "mc": 435, "oc": 37}], "yosh": [{"id": 819365, "mc": 61, "oc": 8}, {"id": 850642, "mc": 878, "oc": 91}, {"id": 863910, "mc": 266, "oc": 66}, {"id": 894795, "mc": 49, "oc": 13}, {"id": 894795, "mc": 49, "oc": 13}], "yonbon": [{"id": 819648, "mc": 108, "oc": 35}], "yokoteh64ninjacat": [{"id": 819863, "mc": 1, "oc": 0}], "yogidamonk": [{"id": 819912, "mc": 220, "oc": 68}], "yourstruely09": [{"id": 819915, "mc": 66, "oc": 18}], "yookie66": [{"id": 820885, "mc": 2, "oc": 0}], "youngbean": [{"id": 821109, "mc": 90, "oc": 15}, {"id": 896252, "mc": 20, "oc": 11}], "yodovan": [{"id": 821982, "mc": 149, "oc": 5}], "yokithao": [{"id": 823174, "mc": 291, "oc": 17}], "yora": [{"id": 823335, "mc": 41, "oc": 6}], "yoldov": [{"id": 825688, "mc": 57, "oc": 16}], "yoob": [{"id": 826144, "mc": 12, "oc": 6}], "youravgben": [{"id": 826215, "mc": 38, "oc": 8}], "yoh": [{"id": 826284, "mc": 89, "oc": 19}, {"id": 879161, "mc": 17, "oc": 2}], "yortu": [{"id": 826421, "mc": 23, "oc": 7}], "yofmz": [{"id": 826695, "mc": 144, "oc": 10}], "yousef": [{"id": 828219, "mc": 1290, "oc": 71}, {"id": 861829, "mc": 32, "oc": 5}, {"id": 866586, "mc": 147, "oc": 12}, {"id": 925017, "mc": 33, "oc": 14}, {"id": 929179, "mc": 22, "oc": 12}], "yorusae": [{"id": 828560, "mc": 114, "oc": 18}], "yourlocalr211": [{"id": 828840, "mc": 14, "oc": 8}], "yorugata": [{"id": 829684, "mc": 18, "oc": 11}], "youleyou": [{"id": 829861, "mc": 35, "oc": 3}], "yomeru": [{"id": 830076, "mc": 646, "oc": 61}], "youtuber": [{"id": 830189, "mc": 97, "oc": 7}, {"id": 831041, "mc": 36, "oc": 13}, {"id": 867741, "mc": 35, "oc": 18}, {"id": 895159, "mc": 1, "oc": 0}, {"id": 895524, "mc": 1, "oc": 0}, {"id": 898771, "mc": 41, "oc": 8}, {"id": 931490, "mc": 63, "oc": 1}], "yougo": [{"id": 830990, "mc": 32, "oc": 2}], "yoast": [{"id": 831184, "mc": 36, "oc": 4}], "youuglyyyy": [{"id": 831378, "mc": 15, "oc": 7}], "yohk3n": [{"id": 832224, "mc": 189, "oc": 8}], "yorda": [{"id": 832235, "mc": 2, "oc": 0}], "youngepilepsy": [{"id": 832625, "mc": 4, "oc": 0}], "yottabite": [{"id": 832991, "mc": 537, "oc": 73}], "yogoo": [{"id": 833105, "mc": 1221, "oc": 96}], "yoregame": [{"id": 833570, "mc": 12, "oc": 5}], "yoakemae": [{"id": 833690, "mc": 33, "oc": 2}], "yopeet": [{"id": 834484, "mc": 3, "oc": 1}], "youngdotaman": [{"id": 834702, "mc": 3, "oc": 2}], "younger": [{"id": 835128, "mc": 705, "oc": 146}], "yordraw": [{"id": 835170, "mc": 18, "oc": 1}], "youn": [{"id": 835356, "mc": 8, "oc": 3}, {"id": 992482, "mc": 16, "oc": 7}], "yourinternetmom": [{"id": 835930, "mc": 289, "oc": 54}], "yourmom": [{"id": 836343, "mc": 10, "oc": 1}], "yoojin": [{"id": 836715, "mc": 23, "oc": 9}], "youngking": [{"id": 837047, "mc": 1, "oc": 0}], "yourot": [{"id": 840729, "mc": 4, "oc": 0}], "youtubeisgood75": [{"id": 840838, "mc": 1, "oc": 0}], "yogazsatria": [{"id": 841054, "mc": 4266, "oc": 292}], "yosila": [{"id": 842247, "mc": 793, "oc": 243}], "yoroi": [{"id": 842845, "mc": 87, "oc": 28}], "yohanne": [{"id": 844326, "mc": 207, "oc": 41}], "yozero": [{"id": 845198, "mc": 73, "oc": 27}], "yosyar": [{"id": 845386, "mc": 4752, "oc": 1877}, {"id": 846733, "mc": 105, "oc": 49}], "yonatan": [{"id": 845463, "mc": 1071, "oc": 67}, {"id": 932139, "mc": 17, "oc": 1}], "yoran": [{"id": 845657, "mc": 21, "oc": 7}], "yorrd": [{"id": 845726, "mc": 107, "oc": 11}], "youssef": [{"id": 845768, "mc": 180, "oc": 18}, {"id": 939210, "mc": 39, "oc": 3}, {"id": 939894, "mc": 19, "oc": 14}, {"id": 957066, "mc": 126, "oc": 24}, {"id": 987881, "mc": 163, "oc": 29}], "yokaitrash": [{"id": 846424, "mc": 90, "oc": 26}], "yousof": [{"id": 846646, "mc": 72, "oc": 6}], "yos": [{"id": 847105, "mc": 80, "oc": 8}, {"id": 886882, "mc": 2, "oc": 1}], "youngg": [{"id": 847197, "mc": 6, "oc": 3}], "youlong": [{"id": 847495, "mc": 879, "oc": 46}], "yosikawa": [{"id": 848358, "mc": 31, "oc": 14}], "youshotdat": [{"id": 848381, "mc": 45, "oc": 8}], "yogesh": [{"id": 848861, "mc": 84, "oc": 1}, {"id": 860531, "mc": 357, "oc": 14}], "yokomaru": [{"id": 849243, "mc": 528, "oc": 15}], "yourmanjam": [{"id": 849338, "mc": 29, "oc": 1}], "yopy": [{"id": 849469, "mc": 37, "oc": 18}], "yokaiskye": [{"id": 850112, "mc": 50, "oc": 10}], "yousukee": [{"id": 851431, "mc": 6, "oc": 1}], "yolexi": [{"id": 852846, "mc": 197, "oc": 18}], "yodazen": [{"id": 853627, "mc": 6, "oc": 5}], "yodtong": [{"id": 855863, "mc": 2165, "oc": 140}], "yoshimoto": [{"id": 856431, "mc": 336, "oc": 5}], "yojellybill": [{"id": 858986, "mc": 4022, "oc": 509}], "youluvgem": [{"id": 859342, "mc": 1343, "oc": 60}], "yomupiiman": [{"id": 859457, "mc": 277, "oc": 123}], "yoshikid": [{"id": 861504, "mc": 100, "oc": 32}], "yolanda": [{"id": 861650, "mc": 205, "oc": 9}], "yodadoggo": [{"id": 862250, "mc": 42, "oc": 12}], "youngbin": [{"id": 862596, "mc": 330, "oc": 80}], "yoshescool": [{"id": 862801, "mc": 436, "oc": 14}], "yori": [{"id": 863033, "mc": 28, "oc": 6}, {"id": 969459, "mc": 164, "oc": 73}], "yoyo1299": [{"id": 863066, "mc": 30, "oc": 5}], "yoboy": [{"id": 863825, "mc": 14, "oc": 7}, {"id": 949256, "mc": 1, "oc": 0}], "yoneyama": [{"id": 865474, "mc": 4, "oc": 1}], "yoll": [{"id": 865777, "mc": 50, "oc": 9}], "yourex": [{"id": 866170, "mc": 7, "oc": 0}], "yotey": [{"id": 866179, "mc": 1, "oc": 1}, {"id": 993818, "mc": 1, "oc": 1}], "yoino": [{"id": 866340, "mc": 521, "oc": 137}], "yovska": [{"id": 866444, "mc": 722, "oc": 98}], "yoplay": [{"id": 866871, "mc": 49, "oc": 12}], "yourevilside": [{"id": 867093, "mc": 1, "oc": 0}], "yourjaydev": [{"id": 867650, "mc": 67, "oc": 14}], "yomama": [{"id": 867861, "mc": 2, "oc": 0}, {"id": 942293, "mc": 42, "oc": 11}], "younglauri": [{"id": 867887, "mc": 78, "oc": 21}], "yodabobobo": [{"id": 868212, "mc": 503, "oc": 46}], "youngman": [{"id": 869020, "mc": 171, "oc": 46}], "yobrotom": [{"id": 869695, "mc": 430, "oc": 79}], "yonush": [{"id": 870284, "mc": 19, "oc": 5}, {"id": 969426, "mc": 42, "oc": 12}], "yorha": [{"id": 870746, "mc": 14, "oc": 7}, {"id": 975968, "mc": 1, "oc": 0}], "yoro1027": [{"id": 871898, "mc": 6307, "oc": 3700}], "yourfren": [{"id": 872103, "mc": 442, "oc": 10}], "yojosherino": [{"id": 872470, "mc": 455, "oc": 105}], "yokusho": [{"id": 872898, "mc": 68, "oc": 19}], "yorozu": [{"id": 873683, "mc": 59, "oc": 6}], "yorkie": [{"id": 873824, "mc": 16, "oc": 1}, {"id": 895021, "mc": 2, "oc": 1}], "yondita": [{"id": 874202, "mc": 102, "oc": 23}], "youby4": [{"id": 874409, "mc": 3911, "oc": 855}], "youei": [{"id": 874833, "mc": 45, "oc": 16}], "youaresatoshi": [{"id": 875222, "mc": 189, "oc": 13}], "yoshe": [{"id": 875402, "mc": 96, "oc": 22}], "yourjar": [{"id": 875684, "mc": 93, "oc": 6}], "yofanzo": [{"id": 875909, "mc": 107, "oc": 23}], "yoslanx": [{"id": 875941, "mc": 48, "oc": 4}], "youwat": [{"id": 876016, "mc": 9, "oc": 3}], "youthoodfink": [{"id": 878961, "mc": 256, "oc": 17}], "yorkie065": [{"id": 879311, "mc": 341, "oc": 49}], "yorth": [{"id": 880008, "mc": 144, "oc": 31}], "youtune": [{"id": 880575, "mc": 1012, "oc": 8}], "yokimommy": [{"id": 880839, "mc": 72, "oc": 36}], "yodaboost": [{"id": 880901, "mc": 42, "oc": 14}], "yogu": [{"id": 882398, "mc": 27, "oc": 3}], "yourlocalduskfox": [{"id": 883023, "mc": 37, "oc": 10}], "yourboyzulu": [{"id": 883199, "mc": 4, "oc": 2}], "youffielz": [{"id": 883761, "mc": 51, "oc": 11}], "yoshijosh": [{"id": 883805, "mc": 20, "oc": 5}], "youtubegamer": [{"id": 883829, "mc": 217, "oc": 19}], "yomamagaming": [{"id": 883839, "mc": 11, "oc": 0}], "yoame": [{"id": 885317, "mc": 3038, "oc": 1111}], "yobun": [{"id": 885390, "mc": 9, "oc": 0}], "yousseftw5": [{"id": 886648, "mc": 342, "oc": 30}], "yozef": [{"id": 887147, "mc": 306, "oc": 11}], "yourblur": [{"id": 887475, "mc": 128, "oc": 46}], "yotsumura": [{"id": 887981, "mc": 179, "oc": 15}], "yokio": [{"id": 888438, "mc": 7, "oc": 1}], "yoshinobu": [{"id": 888465, "mc": 5, "oc": 1}], "yolox": [{"id": 888686, "mc": 44, "oc": 9}], "yosupo": [{"id": 889093, "mc": 185, "oc": 37}], "yok3": [{"id": 889330, "mc": 3, "oc": 0}], "yokaii": [{"id": 889601, "mc": 69, "oc": 18}], "yokii": [{"id": 890061, "mc": 4, "oc": 2}], "yoobrandii": [{"id": 890087, "mc": 36, "oc": 12}], "youkyi": [{"id": 890417, "mc": 158, "oc": 37}], "yosapat": [{"id": 890826, "mc": 11, "oc": 1}], "yourplug": [{"id": 890992, "mc": 891, "oc": 13}], "yomixcci": [{"id": 891397, "mc": 347, "oc": 133}], "yotuelgames07xd": [{"id": 892347, "mc": 1, "oc": 0}], "yodaddyz": [{"id": 892761, "mc": 45, "oc": 24}], "yotech": [{"id": 892899, "mc": 115, "oc": 20}], "yozin": [{"id": 894015, "mc": 35, "oc": 6}], "yozorah": [{"id": 895851, "mc": 14, "oc": 11}], "youraveragelink": [{"id": 896700, "mc": 30, "oc": 14}], "yohanssen": [{"id": 896743, "mc": 17, "oc": 6}], "yourlocalwaifu": [{"id": 897144, "mc": 268, "oc": 24}], "youtoube": [{"id": 897457, "mc": 1, "oc": 0}], "youknowho": [{"id": 897800, "mc": 48, "oc": 3}], "yokhong": [{"id": 898602, "mc": 28, "oc": 4}], "yobbo": [{"id": 899569, "mc": 317, "oc": 8}], "yorulmazizox": [{"id": 899761, "mc": 3758, "oc": 25}], "yoshiko": [{"id": 900070, "mc": 65, "oc": 0}], "yoyomangameur": [{"id": 900152, "mc": 7, "oc": 2}], "yoshitomario": [{"id": 900639, "mc": 341, "oc": 71}], "yogurtg": [{"id": 900704, "mc": 123, "oc": 9}], "yourfriendlytrap": [{"id": 901265, "mc": 155, "oc": 44}], "yoshiblaze": [{"id": 901902, "mc": 36, "oc": 10}], "youthnest": [{"id": 902611, "mc": 6, "oc": 1}], "yourtechbud": [{"id": 903088, "mc": 392, "oc": 15}], "yournakedpainter": [{"id": 903276, "mc": 64, "oc": 9}], "youowemeacoke": [{"id": 903313, "mc": 41, "oc": 10}], "yolowingpixie": [{"id": 903483, "mc": 34, "oc": 13}], "yourclassdad": [{"id": 904322, "mc": 130, "oc": 37}], "yodabird19": [{"id": 904337, "mc": 5, "oc": 2}], "yoshiyuki": [{"id": 904433, "mc": 106, "oc": 42}, {"id": 909350, "mc": 656, "oc": 64}], "youtubeheroofmomentum": [{"id": 904883, "mc": 7, "oc": 1}], "yoolk132": [{"id": 904959, "mc": 5, "oc": 0}], "yosorazvi": [{"id": 905013, "mc": 1037, "oc": 31}], "yourboi776": [{"id": 905029, "mc": 36, "oc": 23}], "yozakura": [{"id": 905442, "mc": 51, "oc": 20}], "yopon": [{"id": 906910, "mc": 100, "oc": 21}, {"id": 985222, "mc": 226, "oc": 36}], "youngdz79": [{"id": 906963, "mc": 14, "oc": 0}], "yolku": [{"id": 907129, "mc": 31, "oc": 4}], "yourregularaussie": [{"id": 908448, "mc": 88, "oc": 18}], "youssifer": [{"id": 909480, "mc": 197, "oc": 22}], "yorokobi": [{"id": 909774, "mc": 99, "oc": 14}], "yourearbiter": [{"id": 910163, "mc": 1, "oc": 0}], "yoyomon": [{"id": 910296, "mc": 354, "oc": 10}], "younesthedefiant": [{"id": 910543, "mc": 111, "oc": 40}], "yoyyeno": [{"id": 910879, "mc": 606, "oc": 45}], "yoshun": [{"id": 911115, "mc": 1642, "oc": 106}], "yoeight": [{"id": 911531, "mc": 43, "oc": 4}], "yoha": [{"id": 911621, "mc": 13, "oc": 5}], "yourlegion": [{"id": 911707, "mc": 898, "oc": 1}], "yorukot": [{"id": 911829, "mc": 711, "oc": 74}], "youloft": [{"id": 911869, "mc": 301, "oc": 10}], "yonosh": [{"id": 912455, "mc": 57, "oc": 13}], "yoga": [{"id": 912534, "mc": 2073, "oc": 95}], "yonko": [{"id": 912865, "mc": 81, "oc": 2}], "yowai": [{"id": 913382, "mc": 194, "oc": 60}, {"id": 956959, "mc": 17, "oc": 3}], "yoboijohn": [{"id": 913633, "mc": 152, "oc": 53}, {"id": 929947, "mc": 6, "oc": 2}], "yomama460": [{"id": 916462, "mc": 20, "oc": 2}], "yoki": [{"id": 918339, "mc": 1, "oc": 0}], "yocactu": [{"id": 919722, "mc": 13, "oc": 3}], "youna": [{"id": 919732, "mc": 85, "oc": 12}], "yoshiboi18303": [{"id": 919745, "mc": 6, "oc": 2}], "yochopkin": [{"id": 920317, "mc": 155, "oc": 33}], "yoshirusano": [{"id": 920547, "mc": 86, "oc": 12}], "yohei": [{"id": 921339, "mc": 327, "oc": 30}, {"id": 968854, "mc": 16, "oc": 4}], "youke": [{"id": 922132, "mc": 48, "oc": 9}], "yourtutor": [{"id": 922242, "mc": 1, "oc": 0}], "younghou": [{"id": 923100, "mc": 611, "oc": 106}], "yorlenc": [{"id": 923237, "mc": 12, "oc": 4}], "yochen014": [{"id": 923297, "mc": 38, "oc": 3}], "yohkay": [{"id": 924364, "mc": 10, "oc": 0}], "youpie": [{"id": 924851, "mc": 296, "oc": 6}], "yollo": [{"id": 926154, "mc": 17, "oc": 7}], "yoshirotv": [{"id": 926304, "mc": 40, "oc": 4}], "yourdadisgone": [{"id": 927349, "mc": 10, "oc": 6}], "yomogi": [{"id": 927359, "mc": 1, "oc": 0}, {"id": 938587, "mc": 39, "oc": 14}], "yourskh": [{"id": 927412, "mc": 193, "oc": 12}], "yoooboiii": [{"id": 927546, "mc": 25, "oc": 7}], "yousele": [{"id": 928618, "mc": 72, "oc": 9}], "yorch": [{"id": 929135, "mc": 201, "oc": 15}], "yous": [{"id": 929194, "mc": 27, "oc": 4}], "yoggi": [{"id": 930142, "mc": 54, "oc": 8}], "younghoodie": [{"id": 930802, "mc": 1, "oc": 0}], "yolli": [{"id": 930888, "mc": 9, "oc": 0}], "youngtripplesix": [{"id": 931355, "mc": 22, "oc": 2}], "youkinow": [{"id": 931697, "mc": 1494, "oc": 82}], "yolomenace001": [{"id": 932222, "mc": 2, "oc": 0}], "yoghnacelli": [{"id": 932290, "mc": 173, "oc": 9}], "yosho": [{"id": 933789, "mc": 35, "oc": 12}], "yohann": [{"id": 934143, "mc": 14, "oc": 3}], "youarecutexd": [{"id": 934269, "mc": 49, "oc": 8}, {"id": 981295, "mc": 45, "oc": 11}], "youthsinbalaclava": [{"id": 934588, "mc": 103, "oc": 14}], "yoshino": [{"id": 937357, "mc": 103, "oc": 38}], "youngskywalker": [{"id": 937459, "mc": 21, "oc": 4}], "yoshia": [{"id": 937832, "mc": 457, "oc": 49}], "yohji": [{"id": 937941, "mc": 13, "oc": 2}], "yova": [{"id": 937993, "mc": 355, "oc": 54}], "yonori": [{"id": 938592, "mc": 39, "oc": 9}], "yoannfleurydev": [{"id": 939877, "mc": 101, "oc": 16}], "yomer": [{"id": 941025, "mc": 44, "oc": 5}], "youri": [{"id": 941035, "mc": 75, "oc": 3}], "yoofie": [{"id": 941080, "mc": 215, "oc": 69}], "youknowwdaijah": [{"id": 942701, "mc": 170, "oc": 34}], "yousseff09": [{"id": 943047, "mc": 6, "oc": 1}], "yolofee": [{"id": 944569, "mc": 225, "oc": 25}], "yourleak": [{"id": 944573, "mc": 756, "oc": 22}], "youmandriver": [{"id": 944741, "mc": 6, "oc": 0}], "yousuf": [{"id": 945045, "mc": 8, "oc": 2}], "yoshinomakoto": [{"id": 945742, "mc": 12, "oc": 2}], "yoan": [{"id": 946093, "mc": 246, "oc": 26}], "yooshi": [{"id": 946318, "mc": 706, "oc": 26}], "yosma": [{"id": 946420, "mc": 25, "oc": 7}], "youtubeplay": [{"id": 947927, "mc": 393, "oc": 49}], "yochi04": [{"id": 948817, "mc": 69, "oc": 10}], "yopi": [{"id": 948883, "mc": 298, "oc": 16}], "yoyle": [{"id": 949103, "mc": 19, "oc": 3}], "yoshimaster114": [{"id": 949537, "mc": 2304, "oc": 79}], "yoschi": [{"id": 950022, "mc": 5, "oc": 1}], "yourfriendrgx": [{"id": 950113, "mc": 31, "oc": 3}], "yoz": [{"id": 950851, "mc": 577, "oc": 39}], "yoseph": [{"id": 950898, "mc": 518, "oc": 24}], "yoshiislander": [{"id": 950950, "mc": 67, "oc": 19}], "yourgib": [{"id": 951427, "mc": 229, "oc": 20}], "youngdale": [{"id": 952446, "mc": 563, "oc": 136}], "yooly": [{"id": 952685, "mc": 583, "oc": 86}], "yoozuisdead": [{"id": 953263, "mc": 15, "oc": 6}], "youmuu": [{"id": 953790, "mc": 2681, "oc": 227}], "yoyoismee": [{"id": 954898, "mc": 245, "oc": 11}], "yocat": [{"id": 955481, "mc": 18, "oc": 3}], "yourmombruhhh": [{"id": 957334, "mc": 16, "oc": 3}], "yowami": [{"id": 957712, "mc": 4, "oc": 0}], "yoro46": [{"id": 958773, "mc": 40, "oc": 3}], "youtubecachoww": [{"id": 962421, "mc": 24, "oc": 3}], "yourpeepee": [{"id": 962450, "mc": 43, "oc": 6}], "yozcoco": [{"id": 962812, "mc": 5, "oc": 0}], "yoare": [{"id": 963198, "mc": 39, "oc": 9}], "yorke": [{"id": 965008, "mc": 93, "oc": 5}], "yoshirinz": [{"id": 967950, "mc": 16, "oc": 3}], "yohemal": [{"id": 968205, "mc": 5, "oc": 3}], "yowillis": [{"id": 968339, "mc": 396, "oc": 53}], "yourgloominaryfriend": [{"id": 969080, "mc": 2, "oc": 1}], "yoimiya57": [{"id": 970255, "mc": 75, "oc": 8}], "yodabz": [{"id": 970324, "mc": 131, "oc": 26}], "yoeruu": [{"id": 971784, "mc": 40, "oc": 4}], "yoboycain23": [{"id": 972687, "mc": 1, "oc": 0}], "yourbrother": [{"id": 972918, "mc": 11, "oc": 3}], "yourlocalgrackle": [{"id": 973228, "mc": 4, "oc": 2}], "yosoywayn": [{"id": 973701, "mc": 74, "oc": 21}], "yosu": [{"id": 973781, "mc": 10, "oc": 6}], "yohangiveabet": [{"id": 974304, "mc": 2081, "oc": 113}], "yourmanadrian": [{"id": 974559, "mc": 32, "oc": 2}], "yow": [{"id": 974895, "mc": 13, "oc": 3}], "younggravedigger": [{"id": 975542, "mc": 512, "oc": 70}], "yoshka": [{"id": 976858, "mc": 288, "oc": 25}], "youcan": [{"id": 976884, "mc": 5, "oc": 1}], "youtubenuddii": [{"id": 977135, "mc": 4, "oc": 0}], "youknowtom": [{"id": 977661, "mc": 9, "oc": 2}], "yogibear": [{"id": 977767, "mc": 45, "oc": 11}], "youraveragegamer31": [{"id": 979068, "mc": 917, "oc": 117}], "yoshaaa": [{"id": 979950, "mc": 36, "oc": 4}], "yotsuba": [{"id": 980465, "mc": 32, "oc": 11}], "yoleodior": [{"id": 980466, "mc": 2, "oc": 0}], "yooper": [{"id": 980559, "mc": 451, "oc": 81}], "yohospill": [{"id": 980727, "mc": 192, "oc": 62}], "yolkhead": [{"id": 981434, "mc": 94, "oc": 9}], "yotaro": [{"id": 981879, "mc": 127, "oc": 5}], "youtu": [{"id": 982317, "mc": 24, "oc": 9}], "yody": [{"id": 984117, "mc": 6, "oc": 1}], "yoku": [{"id": 984785, "mc": 94, "oc": 27}], "yozora": [{"id": 984965, "mc": 24, "oc": 11}], "yoonchul": [{"id": 986263, "mc": 41, "oc": 8}], "yomo": [{"id": 986961, "mc": 270, "oc": 69}], "yohoped": [{"id": 987357, "mc": 6, "oc": 3}], "yoodro": [{"id": 988064, "mc": 211, "oc": 7}], "yoroverseyt": [{"id": 989177, "mc": 36, "oc": 9}], "yog": [{"id": 990024, "mc": 173, "oc": 8}], "yolkiiz": [{"id": 991002, "mc": 44, "oc": 5}], "yokah": [{"id": 991311, "mc": 836, "oc": 227}], "yoa": [{"id": 991395, "mc": 14, "oc": 1}], "yomee": [{"id": 992329, "mc": 39, "oc": 7}], "yocoly": [{"id": 992697, "mc": 134, "oc": 2}], "yomosugara": [{"id": 992704, "mc": 3, "oc": 1}], "yoshhhhh": [{"id": 992813, "mc": 1336, "oc": 27}], "yourmanascii": [{"id": 993551, "mc": 88, "oc": 1}], "yotokendev": [{"id": 994552, "mc": 3, "oc": 0}], "youmgie": [{"id": 995611, "mc": 46, "oc": 19}], "yoongie": [{"id": 996226, "mc": 70, "oc": 31}], "yoyokenwan": [{"id": 996902, "mc": 2915, "oc": 170}], "yop": [{"id": 996995, "mc": 1, "oc": 0}], "yourfriendlyneighborhoodrapist": [{"id": 997892, "mc": 24, "oc": 1}], "yolvenzind": [{"id": 998527, "mc": 14, "oc": 0}], "yonder": [{"id": 999393, "mc": 2, "oc": 0}], "yoshicommitstaxfraud": [{"id": 999944, "mc": 15, "oc": 6}]}