{"60": [{"id": 793547, "mc": 7213, "oc": 278}, {"id": 805709, "mc": 282, "oc": 30}, {"id": 818790, "mc": 1864, "oc": 169}, {"id": 887876, "mc": 4142, "oc": 378}, {"id": 894301, "mc": 199, "oc": 58}, {"id": 902855, "mc": 6255, "oc": 2313}], "60k": [{"id": 822584, "mc": 600, "oc": 170}, {"id": 834243, "mc": 3380, "oc": 147}], "600": [{"id": 921506, "mc": 581, "oc": 22}, {"id": 953242, "mc": 266, "oc": 21}, {"id": 964061, "mc": 12190, "oc": 2011}], "60fp": [{"id": 928446, "mc": 718, "oc": 47}], "606th": [{"id": 991354, "mc": 58, "oc": 14}], "6000": [{"id": 994254, "mc": 5199, "oc": 107}]}