{"dxcezwh": [{"id": 750029, "mc": 1389, "oc": 338}], "dxfrnqe": [{"id": 751119, "mc": 20, "oc": 3}], "dxbevb3": [{"id": 751521, "mc": 2, "oc": 0}], "dxunycsjwj": [{"id": 752531, "mc": 33, "oc": 13}], "dxbfvmz": [{"id": 754751, "mc": 4, "oc": 0}], "dxe6hydpt9": [{"id": 755385, "mc": 4, "oc": 3}], "dxw8jwt": [{"id": 755540, "mc": 19, "oc": 9}], "dxpmczw": [{"id": 756691, "mc": 1, "oc": 0}], "dxtur5whb8": [{"id": 756805, "mc": 62, "oc": 6}], "dxrk": [{"id": 757144, "mc": 2732, "oc": 750}], "dxwzfpm": [{"id": 757396, "mc": 49, "oc": 5}], "dx43sbvuav": [{"id": 758239, "mc": 1673, "oc": 109}], "dxc7ydjagk": [{"id": 758758, "mc": 143, "oc": 16}], "dxcf8abc27": [{"id": 759170, "mc": 14, "oc": 6}], "dxachjm38f": [{"id": 760006, "mc": 25, "oc": 3}], "dxbtpqtjgn": [{"id": 760050, "mc": 43, "oc": 7}], "dxfsqzh4uv": [{"id": 762361, "mc": 127, "oc": 8}], "dxjyte4fae": [{"id": 762965, "mc": 23, "oc": 9}], "dxfyx7e": [{"id": 764140, "mc": 192, "oc": 17}], "dxbtnz2jfe": [{"id": 764325, "mc": 50, "oc": 12}], "dxyepjfe5e": [{"id": 767839, "mc": 4, "oc": 3}], "dxjnjwgxyk": [{"id": 769196, "mc": 13, "oc": 3}], "dxbdyy7": [{"id": 769257, "mc": 877, "oc": 114}], "dxs9ecws8b": [{"id": 769731, "mc": 14, "oc": 1}], "dxbwu3a6rw": [{"id": 769843, "mc": 49, "oc": 21}], "dxtfrmndj": [{"id": 771040, "mc": 91, "oc": 19}], "dxgtwkbdhq": [{"id": 772554, "mc": 26, "oc": 8}], "dxzgkjxwvp": [{"id": 772686, "mc": 663, "oc": 76}], "dxqrg8mnpf": [{"id": 773538, "mc": 656, "oc": 211}], "dxtw7dkawz": [{"id": 773582, "mc": 30, "oc": 4}], "dxxnfyakct": [{"id": 773811, "mc": 92, "oc": 8}], "dxhqwkpfxx": [{"id": 774374, "mc": 1, "oc": 0}], "dxn3kum": [{"id": 774522, "mc": 79, "oc": 21}], "dxshsrskx2": [{"id": 774829, "mc": 6, "oc": 0}], "dx9jskmjzd": [{"id": 774953, "mc": 11, "oc": 3}], "dxbddvbjeh": [{"id": 775143, "mc": 166, "oc": 25}], "dxsy4ur": [{"id": 775206, "mc": 9, "oc": 0}], "dxw2dkp34y": [{"id": 775376, "mc": 24, "oc": 6}], "dxvdcufxj": [{"id": 775863, "mc": 52, "oc": 14}], "dxwgfry": [{"id": 776608, "mc": 1, "oc": 0}], "dxtugfg": [{"id": 778148, "mc": 105, "oc": 1}], "dxdvuqxb9": [{"id": 778207, "mc": 50, "oc": 9}], "dxd": [{"id": 778930, "mc": 1558, "oc": 524}], "dxjdfx66pm": [{"id": 779417, "mc": 3, "oc": 2}], "dxsqgfqkh": [{"id": 779707, "mc": 27, "oc": 7}], "dxrf3yshej": [{"id": 779860, "mc": 511, "oc": 18}], "dxjfvnr": [{"id": 779906, "mc": 14, "oc": 3}], "dxsaadsvvz": [{"id": 780541, "mc": 226, "oc": 11}], "dxujak6vcu": [{"id": 781123, "mc": 48, "oc": 11}], "dxjrtfbazt": [{"id": 781235, "mc": 2, "oc": 0}], "dxu2wr8mjg": [{"id": 782527, "mc": 10484, "oc": 8}], "dxe79rk": [{"id": 782616, "mc": 501, "oc": 105}], "dxvfwfq": [{"id": 782637, "mc": 80, "oc": 21}], "dxfcap7": [{"id": 782922, "mc": 1, "oc": 0}], "dxmygx5wju": [{"id": 783980, "mc": 184, "oc": 40}], "dxbcyjw": [{"id": 784222, "mc": 116, "oc": 23}], "dxbgrpvz3h": [{"id": 784230, "mc": 141, "oc": 7}], "dx9gqme": [{"id": 784441, "mc": 39, "oc": 6}], "dxav8xwmru": [{"id": 784483, "mc": 6871, "oc": 544}], "dxmu34tugv": [{"id": 784626, "mc": 206, "oc": 45}], "dxv4nqj": [{"id": 784828, "mc": 37, "oc": 12}], "dx9keegncm": [{"id": 784974, "mc": 22, "oc": 7}], "dx9jvvk": [{"id": 784975, "mc": 15, "oc": 5}], "dxncera": [{"id": 785046, "mc": 15, "oc": 1}], "dx3jck6s4h": [{"id": 786463, "mc": 12, "oc": 1}], "dxjnawu5m2": [{"id": 786834, "mc": 25, "oc": 4}], "dxqtjcn7fz": [{"id": 787445, "mc": 180, "oc": 15}], "dxhs8nxnbd": [{"id": 787952, "mc": 197, "oc": 32}], "dxxvmwjg35": [{"id": 788711, "mc": 25, "oc": 1}], "dxbbzh2dhk": [{"id": 788926, "mc": 98, "oc": 34}], "dxgdzwk6ut": [{"id": 788995, "mc": 1, "oc": 0}], "dxzdzg8": [{"id": 789000, "mc": 34, "oc": 4}], "dxkdxug22f": [{"id": 789010, "mc": 4604, "oc": 343}], "dxywmev9k5": [{"id": 789724, "mc": 23, "oc": 12}], "dxepx2d": [{"id": 789736, "mc": 3, "oc": 0}], "dxbkgjh": [{"id": 789792, "mc": 10, "oc": 0}], "dxz8rne": [{"id": 790676, "mc": 6, "oc": 3}], "dxttrbnnf9": [{"id": 790794, "mc": 32, "oc": 7}], "dxqwyj3vux": [{"id": 791086, "mc": 67, "oc": 14}], "dxhs8jnt3b": [{"id": 791214, "mc": 25, "oc": 6}], "dxhzavavmk": [{"id": 791548, "mc": 4369, "oc": 1952}], "dxq2ma7hca": [{"id": 791571, "mc": 17, "oc": 9}], "dxrtxcdqge": [{"id": 791723, "mc": 35, "oc": 8}], "dxtzvqw74k": [{"id": 791993, "mc": 136, "oc": 11}], "dxmymre": [{"id": 793551, "mc": 40, "oc": 10}], "dxecdnbpb4": [{"id": 793846, "mc": 8, "oc": 1}], "dxb55nj4tg": [{"id": 794297, "mc": 281, "oc": 130}], "dxmkpphjda": [{"id": 794946, "mc": 25, "oc": 16}], "dxzqmeb": [{"id": 795040, "mc": 1, "oc": 0}], "dxv4kukkxu": [{"id": 795083, "mc": 2904, "oc": 14}], "dxb": [{"id": 795801, "mc": 2518, "oc": 116}], "dxcsszqqep": [{"id": 796076, "mc": 236, "oc": 28}], "dxnrfhh": [{"id": 797000, "mc": 8, "oc": 0}], "dxpz9we": [{"id": 797622, "mc": 47, "oc": 16}], "dxxq2vsf7h": [{"id": 797836, "mc": 2765, "oc": 109}], "dxp9e93pad": [{"id": 798029, "mc": 157, "oc": 50}], "dxrqn88h68": [{"id": 798381, "mc": 56, "oc": 10}], "dxjjb8r2tm": [{"id": 799464, "mc": 7, "oc": 3}], "dxhhahqcrt": [{"id": 800768, "mc": 11, "oc": 3}], "dxunpr5": [{"id": 801157, "mc": 4, "oc": 0}], "dxw3ve5rwe": [{"id": 801434, "mc": 52, "oc": 28}], "dxfejz": [{"id": 801566, "mc": 21, "oc": 8}], "dxhssaz": [{"id": 802343, "mc": 6, "oc": 3}], "dxxsrvczp7": [{"id": 802361, "mc": 6, "oc": 5}], "dxzydak": [{"id": 803055, "mc": 63, "oc": 15}], "dxyjpaq": [{"id": 803840, "mc": 25, "oc": 6}], "dx64vtxn2v": [{"id": 804188, "mc": 73, "oc": 16}], "dxx3htk8nn": [{"id": 804534, "mc": 84, "oc": 4}], "dxvscfqdra": [{"id": 804538, "mc": 21, "oc": 6}], "dxz9n7rtcf": [{"id": 804818, "mc": 77, "oc": 8}], "dxf7esp8d7": [{"id": 804988, "mc": 15, "oc": 6}], "dxh2rak": [{"id": 805070, "mc": 7, "oc": 2}], "dxhz7uw": [{"id": 805219, "mc": 9, "oc": 4}], "dxt2jp36vw": [{"id": 806075, "mc": 99, "oc": 22}], "dxk8q4cwfc": [{"id": 806090, "mc": 2097, "oc": 71}], "dxvbysk": [{"id": 806328, "mc": 22, "oc": 3}], "dxryrwykuh": [{"id": 806589, "mc": 640, "oc": 46}], "dxwdqvgztx": [{"id": 807569, "mc": 262, "oc": 5}], "dxcxkkhffe": [{"id": 807997, "mc": 17, "oc": 0}], "dxnqkw2tyq": [{"id": 808863, "mc": 22, "oc": 10}], "dxyz4jc": [{"id": 809155, "mc": 371, "oc": 24}], "dxauvk6": [{"id": 809420, "mc": 517, "oc": 36}], "dxsahnuz6f": [{"id": 809615, "mc": 36, "oc": 2}], "dxs4jjreuw": [{"id": 809676, "mc": 881, "oc": 156}], "dx4qqdu": [{"id": 809688, "mc": 386, "oc": 166}], "dxap7vf": [{"id": 810658, "mc": 47, "oc": 1}], "dxybhz4pp6": [{"id": 810958, "mc": 10, "oc": 0}], "dxkqvahgub": [{"id": 811233, "mc": 19, "oc": 4}], "dxbtr44tsu": [{"id": 813066, "mc": 7965, "oc": 2361}], "dxsybxt": [{"id": 813147, "mc": 30, "oc": 3}], "dxmrp67w8p": [{"id": 814709, "mc": 7, "oc": 2}], "dxqmcjazua": [{"id": 815891, "mc": 30, "oc": 1}], "dxw99c8": [{"id": 816270, "mc": 23, "oc": 3}], "dxhspqu": [{"id": 816823, "mc": 33, "oc": 4}], "dxydc4d": [{"id": 817777, "mc": 15, "oc": 6}], "dx83xjm": [{"id": 818075, "mc": 13, "oc": 3}], "dxqcafm9r2": [{"id": 819246, "mc": 102, "oc": 5}], "dxkecd8ymu": [{"id": 821474, "mc": 1, "oc": 0}], "dxhtud4vcp": [{"id": 821483, "mc": 43, "oc": 2}], "dxcczd8dw4": [{"id": 821818, "mc": 4, "oc": 2}], "dxsbp5nbyr": [{"id": 821831, "mc": 47, "oc": 21}], "dxjqmhx": [{"id": 822092, "mc": 12, "oc": 1}], "dx3cbxj3me": [{"id": 823354, "mc": 37, "oc": 11}], "dxu4ebkdrw": [{"id": 823359, "mc": 47, "oc": 13}], "dxeksjffcm": [{"id": 823499, "mc": 19, "oc": 2}], "dx6bfx9ztv": [{"id": 824566, "mc": 2, "oc": 0}], "dxmxjka": [{"id": 824802, "mc": 12, "oc": 1}], "dx8zx6ntt9": [{"id": 825977, "mc": 135, "oc": 43}], "dxe5k4nuyt": [{"id": 826662, "mc": 142, "oc": 10}], "dxsngmbsqm": [{"id": 827104, "mc": 1070, "oc": 41}], "dxuvxye": [{"id": 828088, "mc": 75, "oc": 0}], "dxwduw5cnx": [{"id": 828684, "mc": 94, "oc": 19}], "dxzr8dvhty": [{"id": 829886, "mc": 109, "oc": 26}], "dxergpttr3": [{"id": 831597, "mc": 6, "oc": 2}], "dxmkmzna8": [{"id": 832639, "mc": 119, "oc": 14}], "dxxqwah": [{"id": 832764, "mc": 69, "oc": 4}], "dxtync6zv4": [{"id": 832900, "mc": 1, "oc": 0}], "dxfy652bve": [{"id": 832925, "mc": 22, "oc": 4}], "dxg6yd8v4t": [{"id": 833191, "mc": 4130, "oc": 31}], "dxszsaxa94": [{"id": 833244, "mc": 21, "oc": 5}], "dxtxkkzze": [{"id": 833437, "mc": 89, "oc": 30}], "dx9dbz9eqw": [{"id": 833532, "mc": 186, "oc": 52}], "dx3bzgu": [{"id": 833540, "mc": 196, "oc": 20}], "dxcwguv": [{"id": 833757, "mc": 38, "oc": 10}], "dx4nse4ay3": [{"id": 833987, "mc": 251, "oc": 34}], "dxtg8dmfrt": [{"id": 834171, "mc": 186, "oc": 29}], "dxptmfbepx": [{"id": 834305, "mc": 6, "oc": 0}], "dxevrpzyuw": [{"id": 834630, "mc": 80, "oc": 4}], "dxrqxdq4ag": [{"id": 834663, "mc": 3, "oc": 2}], "dxq2jbkhaf": [{"id": 835545, "mc": 2037, "oc": 150}], "dx3spbg": [{"id": 836787, "mc": 12, "oc": 3}], "dx4t4ngbn": [{"id": 837203, "mc": 50, "oc": 3}], "dxxmpym": [{"id": 837207, "mc": 155, "oc": 21}], "dxg5xbz": [{"id": 837592, "mc": 131, "oc": 4}], "dx7rpk59vq": [{"id": 837730, "mc": 20, "oc": 6}], "dxsxfux": [{"id": 838337, "mc": 234, "oc": 21}], "dxt5r3p": [{"id": 838555, "mc": 240, "oc": 2}], "dx9bcpvmt9": [{"id": 839630, "mc": 29, "oc": 7}], "dxujkumyhx": [{"id": 839985, "mc": 29, "oc": 4}], "dxfdyat": [{"id": 840079, "mc": 4, "oc": 1}], "dxevpgdzjv": [{"id": 840679, "mc": 338, "oc": 47}], "dx6xgez": [{"id": 843449, "mc": 107, "oc": 32}], "dxp9vdv5vu": [{"id": 843751, "mc": 39, "oc": 12}], "dx7g3u9": [{"id": 844084, "mc": 87, "oc": 11}], "dxxxeke": [{"id": 845881, "mc": 376, "oc": 14}], "dx9j9cc": [{"id": 846142, "mc": 45, "oc": 8}], "dxwcp2p": [{"id": 846509, "mc": 2, "oc": 0}], "dxfgam3jbm": [{"id": 846689, "mc": 77, "oc": 6}], "dxxcrpybyj": [{"id": 846817, "mc": 162, "oc": 43}], "dxemcsg3xh": [{"id": 847863, "mc": 6, "oc": 0}], "dxh7dbb7bh": [{"id": 848117, "mc": 24, "oc": 5}], "dxbnjykdhb": [{"id": 848833, "mc": 13, "oc": 6}], "dx3umgd": [{"id": 849477, "mc": 30, "oc": 5}], "dxxztgn": [{"id": 849508, "mc": 2, "oc": 1}], "dxenwgw": [{"id": 849522, "mc": 50, "oc": 10}], "dxrfkyycy": [{"id": 849587, "mc": 27, "oc": 4}], "dxjnwnszkf": [{"id": 849603, "mc": 11, "oc": 3}], "dxvuu6e": [{"id": 849713, "mc": 172, "oc": 32}], "dxnbhda": [{"id": 849780, "mc": 36, "oc": 8}], "dxuuh2ucaa": [{"id": 850340, "mc": 8, "oc": 2}], "dxfhzy33nf": [{"id": 850530, "mc": 739, "oc": 37}], "dxcxymbztm": [{"id": 850576, "mc": 13, "oc": 3}], "dxhftn22nr": [{"id": 850592, "mc": 94, "oc": 14}], "dxctchseeu": [{"id": 850972, "mc": 9, "oc": 1}], "dxdfhdg": [{"id": 851096, "mc": 103, "oc": 4}], "dxfrhhzpqd": [{"id": 852702, "mc": 66, "oc": 24}], "dxkwahpbuq": [{"id": 853115, "mc": 2, "oc": 0}], "dxb4dfm": [{"id": 853239, "mc": 12, "oc": 1}], "dxpwv3vwbq": [{"id": 853325, "mc": 18, "oc": 3}], "dxy6s2aq7u": [{"id": 853457, "mc": 24, "oc": 16}], "dxc9dctvsb": [{"id": 853509, "mc": 131, "oc": 16}], "dxqpaqy": [{"id": 853520, "mc": 65, "oc": 2}], "dxgfsxxv6c": [{"id": 854928, "mc": 615, "oc": 27}], "dxccd54gwc": [{"id": 855525, "mc": 603, "oc": 89}], "dxmmx7gzyj": [{"id": 855553, "mc": 19, "oc": 4}], "dxman4gygd": [{"id": 856191, "mc": 25, "oc": 3}], "dxjj3zuwdb": [{"id": 856994, "mc": 1459, "oc": 363}], "dxkg87m3dk": [{"id": 858456, "mc": 258, "oc": 8}], "dx9ztvnacn": [{"id": 858716, "mc": 21, "oc": 4}], "dxxyhkpdrr": [{"id": 858736, "mc": 37, "oc": 8}], "dxtekse": [{"id": 859404, "mc": 10, "oc": 3}], "dxmkbydxxf": [{"id": 859949, "mc": 1, "oc": 0}], "dxvuqus2cm": [{"id": 859950, "mc": 6, "oc": 0}], "dxtervmc6c": [{"id": 860328, "mc": 251, "oc": 37}], "dxymucxhpu": [{"id": 861007, "mc": 17, "oc": 7}], "dxnav3ymjb": [{"id": 861905, "mc": 5, "oc": 1}], "dxbazannrx": [{"id": 862163, "mc": 72, "oc": 9}], "dxwh6fsvh": [{"id": 862258, "mc": 25, "oc": 4}], "dxzg8bz2dq": [{"id": 863072, "mc": 84, "oc": 26}], "dxn4nuh": [{"id": 863107, "mc": 13, "oc": 1}], "dxnf72k4sz": [{"id": 863568, "mc": 7266, "oc": 187}], "dxme7bckga": [{"id": 864876, "mc": 127, "oc": 40}], "dxemfxy": [{"id": 865323, "mc": 667, "oc": 83}], "dxsxt2p": [{"id": 865419, "mc": 55, "oc": 16}], "dxbt6nn": [{"id": 865467, "mc": 1544, "oc": 83}], "dxxmben": [{"id": 865726, "mc": 56, "oc": 8}], "dxsydat": [{"id": 866467, "mc": 3, "oc": 0}], "dxceguz": [{"id": 866994, "mc": 110, "oc": 22}], "dxssmmbben": [{"id": 867206, "mc": 49, "oc": 1}], "dxrjfvwvnx": [{"id": 867707, "mc": 250, "oc": 63}], "dxgj4a39ye": [{"id": 867864, "mc": 53, "oc": 19}], "dxtg3uyvbf": [{"id": 868427, "mc": 18, "oc": 9}], "dxbtppc": [{"id": 868527, "mc": 8, "oc": 3}], "dxjfskw": [{"id": 868704, "mc": 10, "oc": 4}], "dxzb58r": [{"id": 868822, "mc": 444, "oc": 87}], "dxgsmn8jnm": [{"id": 868972, "mc": 763, "oc": 150}], "dxtmschcdw": [{"id": 869520, "mc": 175, "oc": 58}], "dx4dd3kxen": [{"id": 869626, "mc": 23, "oc": 1}], "dxm8jznrtq": [{"id": 870371, "mc": 863, "oc": 298}], "dxzhmfcdkb": [{"id": 870373, "mc": 232, "oc": 33}], "dxzgwvne9": [{"id": 870659, "mc": 4, "oc": 2}], "dxzd6ays7z": [{"id": 871344, "mc": 84, "oc": 20}], "dxfcnwpqku": [{"id": 871347, "mc": 490, "oc": 107}], "dxdxsxzdvd": [{"id": 871462, "mc": 9, "oc": 1}], "dxb9txztan": [{"id": 871541, "mc": 21, "oc": 6}], "dxejqzgmrd": [{"id": 871842, "mc": 20, "oc": 4}], "dxr4etpdkt": [{"id": 872391, "mc": 36, "oc": 12}], "dxwmn5aqzm": [{"id": 874899, "mc": 14, "oc": 4}], "dxa73u": [{"id": 875269, "mc": 92, "oc": 12}], "dxmfwm4cgu": [{"id": 875318, "mc": 9, "oc": 5}], "dxpjqzq": [{"id": 875587, "mc": 1, "oc": 0}], "dxctdwg": [{"id": 875779, "mc": 5704, "oc": 736}], "dxsfa27tsc": [{"id": 875961, "mc": 97, "oc": 31}], "dxd44nkca": [{"id": 876144, "mc": 14445, "oc": 4215}], "dxe4mpq3pv": [{"id": 876156, "mc": 213, "oc": 41}], "dxn4zpxvkt": [{"id": 876638, "mc": 109, "oc": 17}], "dxqvf5huuj": [{"id": 876829, "mc": 59, "oc": 3}], "dxdhkxtcfc": [{"id": 877185, "mc": 23, "oc": 2}], "dxrspkct29": [{"id": 878027, "mc": 800, "oc": 288}], "dx2mypr": [{"id": 878696, "mc": 598, "oc": 119}], "dxfqgsx": [{"id": 878798, "mc": 54, "oc": 13}], "dxeexsdvbp": [{"id": 879437, "mc": 3, "oc": 1}], "dxm89crdtv": [{"id": 879543, "mc": 106, "oc": 19}], "dxasrtp": [{"id": 879639, "mc": 408, "oc": 74}], "dx4cafph3": [{"id": 881115, "mc": 222, "oc": 15}], "dxqdu4fvbf": [{"id": 883202, "mc": 45, "oc": 5}], "dxk8qhyxsq": [{"id": 883522, "mc": 181, "oc": 55}], "dxvqjkvcwc": [{"id": 883852, "mc": 5, "oc": 1}], "dxvet6wzgr": [{"id": 884864, "mc": 1, "oc": 0}], "dx4mbanwmx": [{"id": 885016, "mc": 159, "oc": 14}], "dxshxck": [{"id": 885313, "mc": 1, "oc": 0}], "dxesqzv": [{"id": 886025, "mc": 4, "oc": 1}], "dxvmmdfpbq": [{"id": 886194, "mc": 11, "oc": 3}], "dxvcsgy": [{"id": 886950, "mc": 11, "oc": 1}], "dxwu9kk": [{"id": 887163, "mc": 36, "oc": 9}], "dxngpmf": [{"id": 887193, "mc": 37, "oc": 6}], "dxgawwf": [{"id": 888332, "mc": 1, "oc": 0}], "dxctecn": [{"id": 888382, "mc": 11203, "oc": 48}], "dxb58f": [{"id": 888470, "mc": 7, "oc": 3}], "dxdp84atee": [{"id": 889084, "mc": 47, "oc": 12}], "dxydk4pwf5": [{"id": 889131, "mc": 649, "oc": 48}], "dxw3wya2u": [{"id": 890044, "mc": 16, "oc": 7}], "dxgscdmpd4": [{"id": 890401, "mc": 58, "oc": 18}], "dxf64y3f3k": [{"id": 890782, "mc": 2, "oc": 0}], "dxjagcgapy": [{"id": 891410, "mc": 82, "oc": 7}], "dxddzqqwr9": [{"id": 891936, "mc": 33, "oc": 11}], "dxx2pba": [{"id": 892847, "mc": 1722, "oc": 264}], "dxab9yqg4y": [{"id": 893167, "mc": 41, "oc": 6}], "dxcc4j2udj": [{"id": 894162, "mc": 75, "oc": 21}], "dxczm5w7vf": [{"id": 894908, "mc": 4, "oc": 0}], "dxcascy": [{"id": 895518, "mc": 67, "oc": 21}], "dxbxtac": [{"id": 896065, "mc": 20, "oc": 4}], "dxcphk8xrp": [{"id": 896135, "mc": 1744, "oc": 209}], "dxjmuvam4q": [{"id": 896291, "mc": 486, "oc": 81}], "dxmynb8": [{"id": 896347, "mc": 477, "oc": 46}], "dxg93nebr": [{"id": 896474, "mc": 92, "oc": 4}], "dx5e7wmkph": [{"id": 897643, "mc": 31, "oc": 4}], "dxwmcctmwy": [{"id": 897835, "mc": 102, "oc": 40}], "dxgj8k7": [{"id": 897910, "mc": 133, "oc": 8}], "dxpgmsrcam": [{"id": 898643, "mc": 73, "oc": 29}], "dx6qdjr": [{"id": 898725, "mc": 87, "oc": 6}], "dxev6k9eqr": [{"id": 898753, "mc": 4, "oc": 1}], "dxqeedww8c": [{"id": 898972, "mc": 4, "oc": 2}], "dxxuvy": [{"id": 899060, "mc": 148, "oc": 14}], "dxn4hqe": [{"id": 899113, "mc": 140, "oc": 0}], "dxe7e24": [{"id": 899213, "mc": 50, "oc": 9}], "dxbbvff": [{"id": 899396, "mc": 3, "oc": 0}], "dxzsgdrrpj": [{"id": 899973, "mc": 19, "oc": 8}], "dxmgdrzay4": [{"id": 900912, "mc": 5, "oc": 4}], "dxhxjqc2ag": [{"id": 900935, "mc": 76, "oc": 6}], "dxap99wy2x": [{"id": 901677, "mc": 4036, "oc": 1365}], "dx8bsdfh9g": [{"id": 901890, "mc": 6, "oc": 3}], "dxud6qt": [{"id": 902091, "mc": 2, "oc": 1}], "dxgkmbdqu3": [{"id": 903588, "mc": 1276, "oc": 90}], "dxynxyxbbz": [{"id": 903663, "mc": 1, "oc": 0}], "dxkctdmr7p": [{"id": 904033, "mc": 89, "oc": 10}], "dxt6h9fcvm": [{"id": 904046, "mc": 45, "oc": 15}], "dxu2wxut9n": [{"id": 904703, "mc": 46, "oc": 18}], "dx2qjccuaq": [{"id": 904778, "mc": 118, "oc": 51}], "dx3strnh39": [{"id": 906738, "mc": 2, "oc": 0}], "dx9xqpz": [{"id": 907724, "mc": 117, "oc": 16}], "dxqktgp": [{"id": 908393, "mc": 5, "oc": 1}], "dxq4f9scw7": [{"id": 909660, "mc": 1430, "oc": 198}], "dxdyujavtd": [{"id": 909692, "mc": 6, "oc": 3}], "dxfudhavyh": [{"id": 909724, "mc": 6, "oc": 0}], "dxxfjcruay": [{"id": 909795, "mc": 261, "oc": 17}], "dxuwtpzpjj": [{"id": 910029, "mc": 324, "oc": 71}], "dxwhkxk3sh": [{"id": 910454, "mc": 7, "oc": 4}], "dx6xsc2gdk": [{"id": 910537, "mc": 2675, "oc": 272}], "dxzxexp": [{"id": 911073, "mc": 33, "oc": 2}], "dxjudsv": [{"id": 911933, "mc": 10, "oc": 1}], "dxrmvh3szr": [{"id": 913613, "mc": 14, "oc": 3}], "dx6nakv": [{"id": 914401, "mc": 269, "oc": 15}], "dx4yq8bccz": [{"id": 914751, "mc": 49, "oc": 6}], "dx6wtu2589": [{"id": 914910, "mc": 49, "oc": 8}], "dxhe7rsnaz": [{"id": 915203, "mc": 4, "oc": 0}], "dxfgnsxnxg": [{"id": 915295, "mc": 5, "oc": 0}], "dxqzm4qtne": [{"id": 918286, "mc": 3, "oc": 2}], "dxfhb3gnq4": [{"id": 919579, "mc": 30, "oc": 5}], "dxmemdqg39": [{"id": 919941, "mc": 23, "oc": 6}], "dxjsj9m": [{"id": 919955, "mc": 101, "oc": 12}], "dx3mvbt": [{"id": 920677, "mc": 16, "oc": 3}], "dxbk6ztb2x": [{"id": 920695, "mc": 388, "oc": 151}], "dxbsyyyup2": [{"id": 921267, "mc": 1408, "oc": 256}], "dxychyzr7e": [{"id": 921285, "mc": 2, "oc": 0}], "dx3p7k5uty": [{"id": 921554, "mc": 105, "oc": 16}], "dxzeg7unzt": [{"id": 921635, "mc": 200, "oc": 49}], "dxtwj8wee6": [{"id": 921699, "mc": 133, "oc": 28}], "dxubrz5r7e": [{"id": 921761, "mc": 241, "oc": 20}], "dxgmxyeubu": [{"id": 921956, "mc": 163, "oc": 20}], "dx3emdsmaw": [{"id": 922175, "mc": 12, "oc": 6}], "dxsvmze": [{"id": 922325, "mc": 33, "oc": 4}], "dx3dq6f": [{"id": 922380, "mc": 5, "oc": 1}], "dxaqja4": [{"id": 923205, "mc": 13, "oc": 1}], "dxeu5pu4h6": [{"id": 923810, "mc": 210, "oc": 51}], "dxwbsyy6z3": [{"id": 925024, "mc": 73, "oc": 7}], "dxghehaacp": [{"id": 925993, "mc": 14, "oc": 0}], "dxyfmjze9g": [{"id": 927282, "mc": 80, "oc": 27}], "dxxvm6eck": [{"id": 927573, "mc": 233, "oc": 7}], "dxzdqnu": [{"id": 928055, "mc": 1051, "oc": 173}], "dx88n4wtxt": [{"id": 928368, "mc": 10, "oc": 3}], "dxaeed7": [{"id": 929311, "mc": 3, "oc": 1}], "dxdasvqu9n": [{"id": 929907, "mc": 27, "oc": 1}], "dxbukc5zzz": [{"id": 930225, "mc": 186, "oc": 24}], "dxn64amq25": [{"id": 930831, "mc": 1154, "oc": 69}], "dxtxwq2": [{"id": 931266, "mc": 14, "oc": 5}], "dx6qczk": [{"id": 931984, "mc": 4, "oc": 0}], "dxpujhzy4w": [{"id": 932054, "mc": 27, "oc": 4}], "dxehvdb": [{"id": 932338, "mc": 12, "oc": 3}], "dxd5sa2m97": [{"id": 932493, "mc": 169, "oc": 40}], "dxpg2bjkjw": [{"id": 933735, "mc": 27, "oc": 7}], "dxrwcqwmgm": [{"id": 933854, "mc": 58, "oc": 14}], "dxgezyx": [{"id": 933879, "mc": 117, "oc": 14}], "dxmfpre8hz": [{"id": 934492, "mc": 1, "oc": 1}], "dxztrbf3z8": [{"id": 934970, "mc": 8, "oc": 4}], "dxkumwruq9": [{"id": 935293, "mc": 44, "oc": 9}], "dx8d6dkgcu": [{"id": 935936, "mc": 42, "oc": 7}], "dxuvbjpfzc": [{"id": 935997, "mc": 599, "oc": 55}], "dxbg7kyprb": [{"id": 936132, "mc": 14, "oc": 0}], "dxkcbj9wwf": [{"id": 936192, "mc": 5, "oc": 0}], "dxxpy4b": [{"id": 936267, "mc": 8, "oc": 0}], "dxgmahp7t5": [{"id": 936683, "mc": 51, "oc": 1}], "dxxyvyx": [{"id": 937555, "mc": 4, "oc": 1}], "dxbgchfw9x": [{"id": 938556, "mc": 7, "oc": 6}], "dxes6rytaq": [{"id": 939353, "mc": 1590, "oc": 78}], "dxjjeptf5r": [{"id": 940274, "mc": 26, "oc": 3}], "dxrgjekcdx": [{"id": 941287, "mc": 90, "oc": 3}], "dxfxee3": [{"id": 941442, "mc": 77, "oc": 22}], "dxn3qzk": [{"id": 941482, "mc": 7, "oc": 0}], "dxngjptc8b": [{"id": 941828, "mc": 54, "oc": 12}], "dx4tswaueh": [{"id": 942875, "mc": 212, "oc": 20}], "dx3uft": [{"id": 943329, "mc": 3, "oc": 0}], "dxp6xuvhht": [{"id": 944382, "mc": 1, "oc": 0}], "dxsm4cv6dk": [{"id": 945363, "mc": 116, "oc": 17}], "dxbgmrtrbp": [{"id": 945950, "mc": 3, "oc": 0}], "dxaedma": [{"id": 945959, "mc": 32, "oc": 5}], "dxwwdrhvze": [{"id": 946161, "mc": 2150, "oc": 195}], "dxudthascc": [{"id": 946559, "mc": 2, "oc": 0}], "dxermkgcsa": [{"id": 946947, "mc": 7, "oc": 3}], "dxy9zxz": [{"id": 947120, "mc": 76, "oc": 11}], "dxszwvbsbv": [{"id": 947717, "mc": 95, "oc": 15}], "dx4rkxy2p6": [{"id": 948171, "mc": 16, "oc": 7}], "dx647z28dy": [{"id": 948417, "mc": 182, "oc": 24}], "dx9jfmu": [{"id": 948929, "mc": 209, "oc": 41}], "dx6r3uvf9d": [{"id": 949110, "mc": 55, "oc": 9}], "dxjr4akcyg": [{"id": 949380, "mc": 82, "oc": 17}], "dxz8cra": [{"id": 949770, "mc": 64, "oc": 2}], "dxxxsst": [{"id": 950758, "mc": 16, "oc": 4}], "dxtf8c4": [{"id": 950761, "mc": 676, "oc": 27}], "dxpgykq": [{"id": 950981, "mc": 3, "oc": 1}], "dxje9s2mmv": [{"id": 952169, "mc": 882, "oc": 202}], "dxfqbe4wad": [{"id": 952606, "mc": 6, "oc": 4}], "dxckqvv": [{"id": 952943, "mc": 144, "oc": 9}], "dxp4vvfpcr": [{"id": 953779, "mc": 33, "oc": 11}], "dxgwjtjjau": [{"id": 954150, "mc": 75, "oc": 11}], "dxk9en2ukm": [{"id": 955445, "mc": 121, "oc": 9}], "dxsftu": [{"id": 955807, "mc": 2, "oc": 1}], "dx3mhxvf76": [{"id": 955830, "mc": 21, "oc": 6}], "dxtjegc": [{"id": 956779, "mc": 3, "oc": 1}], "dx4c54b": [{"id": 956830, "mc": 42, "oc": 1}], "dxn7gnc": [{"id": 957578, "mc": 6, "oc": 0}], "dxgkrnj": [{"id": 957680, "mc": 15, "oc": 1}], "dxxvydwssg": [{"id": 958750, "mc": 43, "oc": 6}], "dxweu6gmfy": [{"id": 958967, "mc": 75, "oc": 28}], "dxnkghnkjv": [{"id": 959777, "mc": 23, "oc": 6}], "dxwqgzazzb": [{"id": 959795, "mc": 18543, "oc": 4450}], "dx3sg48": [{"id": 960293, "mc": 31, "oc": 8}], "dxpkkna": [{"id": 960572, "mc": 289, "oc": 57}], "dxpmfaarwm": [{"id": 960674, "mc": 468, "oc": 30}], "dxzurte": [{"id": 960847, "mc": 58, "oc": 5}], "dxwjngmbpj": [{"id": 961342, "mc": 5, "oc": 2}], "dx9mg38ygw": [{"id": 961550, "mc": 37, "oc": 9}], "dxsbyspbhw": [{"id": 962306, "mc": 29, "oc": 4}], "dxvnvyndmn": [{"id": 962329, "mc": 39, "oc": 5}], "dxnvuza": [{"id": 963590, "mc": 352, "oc": 80}], "dxnz8az7sc": [{"id": 963759, "mc": 32, "oc": 8}], "dxmmpdycmh": [{"id": 963950, "mc": 20, "oc": 1}], "dx8tgf2": [{"id": 965047, "mc": 24, "oc": 8}], "dxvxyrqc3v": [{"id": 965576, "mc": 103, "oc": 22}], "dxxedykdfj": [{"id": 965752, "mc": 10, "oc": 1}], "dxg9jhhrx8": [{"id": 965817, "mc": 328, "oc": 18}], "dxaspz5": [{"id": 966608, "mc": 2, "oc": 2}], "dxzhwpf": [{"id": 966857, "mc": 793, "oc": 63}], "dxafuqf9v": [{"id": 967042, "mc": 37, "oc": 7}], "dxfxdw5g94": [{"id": 967524, "mc": 100, "oc": 20}], "dxhjht6xjj": [{"id": 967658, "mc": 972, "oc": 71}], "dxgjssd": [{"id": 967988, "mc": 9, "oc": 0}], "dxnfyfy": [{"id": 968088, "mc": 54, "oc": 8}], "dx3h2snkrr": [{"id": 968385, "mc": 2278, "oc": 60}], "dxn87wxetc": [{"id": 969328, "mc": 926, "oc": 55}], "dxfssmzjyq": [{"id": 969436, "mc": 268, "oc": 5}], "dxpr99t4vw": [{"id": 969785, "mc": 505, "oc": 11}], "dx5xaeq5mq": [{"id": 970324, "mc": 131, "oc": 26}], "dx2uhrkvgy": [{"id": 970725, "mc": 4, "oc": 2}], "dxbhefrykm": [{"id": 971048, "mc": 55, "oc": 17}], "dxkjvtpaaq": [{"id": 971943, "mc": 11, "oc": 0}], "dxfebs6ae8": [{"id": 972208, "mc": 616, "oc": 36}], "dxp4jz574q": [{"id": 973096, "mc": 662, "oc": 31}], "dxufjk": [{"id": 973143, "mc": 94, "oc": 13}], "dxu9kudjtz": [{"id": 973625, "mc": 206, "oc": 10}], "dxrkc57": [{"id": 973759, "mc": 26, "oc": 8}], "dxkmaf2": [{"id": 974091, "mc": 307, "oc": 33}], "dxrjv4ammh": [{"id": 974103, "mc": 57, "oc": 13}], "dxpshztgzy": [{"id": 975110, "mc": 29, "oc": 6}], "dxgz3aztsb": [{"id": 975303, "mc": 5190, "oc": 1006}], "dxkmc84amk": [{"id": 975484, "mc": 49, "oc": 16}], "dx7xae6a5": [{"id": 975678, "mc": 7, "oc": 6}], "dxpjzxtxpw": [{"id": 975711, "mc": 414, "oc": 14}], "dxfgzymtsj": [{"id": 976240, "mc": 9, "oc": 0}], "dxwenwp": [{"id": 976502, "mc": 42, "oc": 14}], "dxdezurf8": [{"id": 976656, "mc": 13, "oc": 7}], "dxq2dktx7m": [{"id": 976804, "mc": 23, "oc": 8}], "dxwk4qpcuc": [{"id": 976828, "mc": 68, "oc": 21}], "dxjq77y": [{"id": 978058, "mc": 30, "oc": 9}], "dxuudjkehm": [{"id": 979502, "mc": 1141, "oc": 190}], "dxq8hq3rwn": [{"id": 979592, "mc": 7, "oc": 1}], "dxyqww9qnc": [{"id": 980152, "mc": 2376, "oc": 176}], "dxmwxde": [{"id": 980620, "mc": 3, "oc": 2}], "dxurgyxtuc": [{"id": 981247, "mc": 542, "oc": 159}], "dxjadpz": [{"id": 981807, "mc": 6, "oc": 1}], "dxnxng98f6": [{"id": 982065, "mc": 308, "oc": 2}], "dxhbnsn": [{"id": 982160, "mc": 30, "oc": 0}], "dxnxc7gfpk": [{"id": 982599, "mc": 65, "oc": 14}], "dxnfxdmauu": [{"id": 982696, "mc": 29, "oc": 8}], "dx2pdhgxrt": [{"id": 983508, "mc": 19, "oc": 5}], "dxatjzqba7": [{"id": 983682, "mc": 196, "oc": 18}], "dx3myt4": [{"id": 983826, "mc": 37, "oc": 12}], "dxmahsh": [{"id": 984652, "mc": 408, "oc": 54}], "dxgvejszeg": [{"id": 985006, "mc": 1273, "oc": 11}], "dx7rb2dtmq": [{"id": 985177, "mc": 1094, "oc": 108}], "dxqfcarsd4": [{"id": 986496, "mc": 2, "oc": 0}], "dxnpdmukxt": [{"id": 986853, "mc": 16, "oc": 7}], "dx4gxfm": [{"id": 988296, "mc": 145, "oc": 23}], "dxyvdj9": [{"id": 988297, "mc": 368, "oc": 16}], "dx4xsqknbe": [{"id": 988499, "mc": 219, "oc": 35}], "dxacsxp": [{"id": 991045, "mc": 1, "oc": 0}], "dxzmgzfksv": [{"id": 991445, "mc": 18, "oc": 0}], "dxfurwd": [{"id": 991482, "mc": 240, "oc": 13}], "dxrfbec": [{"id": 991811, "mc": 4, "oc": 0}], "dxvyv2x": [{"id": 993332, "mc": 105, "oc": 6}], "dxn4cyu6aj": [{"id": 993403, "mc": 8, "oc": 2}], "dxwxfcszwu": [{"id": 993793, "mc": 41, "oc": 10}], "dxezt5x": [{"id": 993901, "mc": 39, "oc": 4}], "dxzttzpyhy": [{"id": 994180, "mc": 78, "oc": 6}], "dxxnzu8": [{"id": 994369, "mc": 48, "oc": 9}], "dxn3rme6rb": [{"id": 994416, "mc": 31, "oc": 6}], "dxrknpcptq": [{"id": 995122, "mc": 12, "oc": 1}], "dxdkfam": [{"id": 996833, "mc": 326, "oc": 58}], "dx7343tex3": [{"id": 996925, "mc": 286, "oc": 49}], "dxzysyzxbk": [{"id": 998160, "mc": 1, "oc": 0}], "dxhs6xgphr": [{"id": 999053, "mc": 45, "oc": 8}], "dxbzcvfmsu": [{"id": 999440, "mc": 758, "oc": 22}], "dx5qqyf": [{"id": 999661, "mc": 286, "oc": 2}]}