{"immortality": [{"id": 758306, "mc": 108, "oc": 25}], "imperfect": [{"id": 764899, "mc": 35079, "oc": 103}], "imposter": [{"id": 786865, "mc": 21, "oc": 5}], "imperialcsgo": [{"id": 795730, "mc": 2863, "oc": 578}], "imanu": [{"id": 822694, "mc": 3039, "oc": 281}], "imbixu": [{"id": 844052, "mc": 65087, "oc": 765}], "immt": [{"id": 847604, "mc": 1568, "oc": 18}], "image": [{"id": 853408, "mc": 238, "oc": 13}], "imaginarymonster": [{"id": 856623, "mc": 153, "oc": 33}], "imyi": [{"id": 870056, "mc": 951, "oc": 135}], "imba": [{"id": 875898, "mc": 315, "oc": 69}], "imbica": [{"id": 885478, "mc": 2978, "oc": 247}], "imakuni": [{"id": 900431, "mc": 1354, "oc": 720}], "impostor": [{"id": 921679, "mc": 1587, "oc": 203}], "imacten": [{"id": 924805, "mc": 10372, "oc": 2578}], "impulse": [{"id": 932136, "mc": 2908, "oc": 174}], "immabunny": [{"id": 941310, "mc": 387, "oc": 177}], "imcoty": [{"id": 941526, "mc": 1584, "oc": 213}], "imvuofficial": [{"id": 947714, "mc": 45858, "oc": 2285}], "immo": [{"id": 968500, "mc": 8619, "oc": 1084}], "immortalz": [{"id": 976532, "mc": 879, "oc": 202}], "imadrum": [{"id": 981920, "mc": 1367, "oc": 302}]}